[{"_id":"6a2bb882cacdf1853c71c320","field":"釣り","type":"distilled","category":"発見","subcategory":"","content":"ルアーの着底を待つ間や、底を取りながら引くといった、ボトム（底）を意識したアプローチにおいて魚がヒットしている。","webSources":[],"supportingExperiences":[],"contradictingExperiences":[],"confidenceScore":0.65,"sourceKnowledgeId":null,"tags":[],"folderId":null,"createdAt":"2026-06-12T07:42:58.341Z","__v":0},{"_id":"6a26dd7bc33063ac9c3937d9","field":"釣り","type":"hypothesis","category":"ルアーカラー","subcategory":"","content":"澄み潮やプレッシャーが高い状況下の木曽川において、背景に溶け込みやすい半透明なゴースト系カラーを使用することで、シーバスに違和感を与えずバイトを誘発できる。","webSources":[{"field":"釣り","query":"木曽川で反応のいいルアーカラーについて","results":[{"title":"【木曽川2020】シーバスゲーム攻略法 釣れるルアー＆釣り方を解説","url":"https://tsurinews.jp/110712","snippet":"次に赤系が少しでも入っているルアーも、強い反応が得られる。赤系はスローリトリーブをすると、魚の反応がいいため覚えていてほしい。 赤金. 干潮間際や"},{"title":"木曽川河口の釣り場｜ルアー・投げ釣りの人気スポット。駐車スペース・トイレ・空撮マップで確認｜汽水の釣りで成果を出す！","url":"https://turiniikou.com/home/map-mie-kita/map-mie-hokubu/point-kisogawa","snippet":"# 木曽川河口の釣り｜シーバス・マゴチが釣れる！│釣り場情報とマップ. 木曽川河口エリアで釣りをする際に知っておきたい情報を整理しました。現地調査で見てきた堤防・足場の状態や、季節ごとの魚の反応など、現地のありのままの情報になります。地図と一緒に、釣行前のシミュレーション用としてご活用いただければ幸いです。. ## 木曽川河口の釣り場. ## 🛰️ 空から木曽川河口の釣り場をチェック. ### マークしたポイント. ## 🏖️ 釣り場の紹介 | 木曽川河口. ### 木曽川河口の特徴. 過去の岸釣りでの情報からは、シーバスに関しては木曽川河口の方がランカーサイズ（80cm以上）の情報が多く出ており、中には90cm以上の情報が複数あるなど、木曽川河口のポテンシャルの高さを感じさせます。. ちなみに、シーバスには主に3種類の魚種があり、スズキ（マルスズキ）、ヒラスズキ、タイリクスズキが一般的にシーバスと呼ばれます。そして、シーバスの岸（磯も含む）釣りでの日本記録はどれくらいかというと、2006年11月に茨城県涸沼川で釣られたスズキが107cm、9.5㎏の記録があります。. ### 木曽川河口で人気のある魚種. ### 注意すべき情報. ### 過去の代表的な釣果情報. ※　イラスト地図上に ●(青い丸）で示したポイントは通称円盤と言われ足場がよく釣りをしやすい人気のポイントです。ただし、釣りを行う方向によっては根がかりをすることが多いという情報もあります。現地では根がかりに注意しながら釣りを行ってください。. ※この釣り場は堤防下へ車で入ることで釣りやすくなります。駐車場の問題、釣り座への移動の問題が解決し、スムーズに釣りが可能になります。このページの下方に記載している方法でカギをかりると、木曽川河口の南側堤防沿いに数か所ある入り口から中に入ることができます。是非ともご活用ください。. ### 🚩ちなみに、似たような雰囲気の釣り場はこちらもおすすめです：. ### 🚩ちなみに、近隣のマゴチが釣れやすい釣り場はこちらもおすすめです：. ### 🚩ちなみに、近隣のシーバスが釣れやすい釣り場はこちらもおすすめです：. ## 🎣 季節ごとに釣れる魚 | 木曽川河口. ### 春（3月～5月）. ### 夏（6月～8月）. シーバス・マゴチ・ウナギ・クロダイ（キビレを含む）・テナガエビ. ### 秋（9月～11月）. シーバス・マゴチ・クロダイ（キビレを含む）・ヒラメ・ハゼ・ボラ. ### 冬（12月～2月）. ## 📍 当たるか外れるかは別として、4月～6月の注目魚 | 木曽川河口. #### **1.シーバス**. **一般的な4月～6月の特徴**：4月は「バチ抜け」によるナイトゲームが期待できます。5月・6月になるとハク（ボラの稚魚）などの小魚を追うようになり、日中のデイゲームでも活性が高まるとされます。. **当ポイントでの特徴**：例年通りであれば、4月は好調ですが、5月～6月と徐々に釣果は低下傾向にあります。. **釣り方**：ルアー釣り（ワームを含む）が中心となります。電気ウキやブッコミ釣りも効果的です。. **サイズ**：4月は40～50cmが狙えます。6月までは50cm級も狙えますが、20～30cmの小型が増える傾向にあります。掲載時点の4月はランカーサイズ（80cm以上）の情報があり、期待できるシーズンです。. **一般的な4月～6月の特徴**：4月から産卵のために浅場へ移動を開始し、5月・6月はハイシーズンに突入します。産卵のために接岸する良型個体をルアーで狙える時期です。. **当ポイントでの特徴**：早い年で4月中旬、例年通りだと4月下旬頃から釣果が上がっていく傾向にあります。過去情報から、このポイントでは春のピークは5月に訪れます。. **サイズ**：サイズは30～50cmが中心で、マーゴン（60cm以上）の情報が複数ある時期になり、期待は高まります。. **時間帯**：朝・夕のマズメ時が中心となりますが、日中でも期待できます。ただし、マーゴン（60cm以上）を狙うのであれば、朝・夕のマズメは外せません。当サイトのデータでは、マーゴン（60cm以上）はマズメ時に実績が多い傾向にあります。. 1.**ウナギ**：5月頃から釣れ出す傾向にあります。例年ですと、6月はさらに釣果が伸びます。土用の丑の日に向けて釣り人も増える傾向にあります。時間帯は基本的には夜間が中心となります。夕マズメ～夜22時頃までが一般的に釣れやすいと言われる時間ですが、筆者も同じような印象です。19時頃に釣れやすいという話をよく聞きますが、筆者は20時～22時が勝負だと思っています。帰って寝たい時間帯ですが、過去の経験上は粘った方が良い時間帯です。ただし、筆者は家族で食べる2～3匹を釣れれば帰る方式をとっています。. 釣り方はぶっこみ釣りが中心となります。エサはドバミミズ、アオイソメ、アケミ貝などいろいろ使われます。筆者はアオイソメをよく使いますが、タイミングによってはセイゴやクロダイ（小）などの外道も多く釣れます。外道も楽しみながら釣りをする場合には有効です。. 2.**クロダイ**：情報は限られていますが、ポツポツ釣れる傾向にあります。サイズはまずまずで45cm級の情報が多く、年なし（50cm以上）の話も聞かれます。釣り方はチニングと言われるルアー釣り（ワームを含む）が多く、シーバスやマゴチとともにルアーで狙うことができます。4月～5月は一般的に乗っ込みと言われる時期で、クロダイの産卵時期にあたり、浅場で捕食することが多くなるとされており、期待が高まる時期です。. 3.**ボラ**：多くはありませんが、釣れることがあります。中には50cm級も釣れるのでタモ網等の装備の準備が必要です。ボラは1日を通して狙える魚で、この場所ではルアー釣りでのスレがかり（口以外に針がかかる）でよく釣れる傾向にあります。もし、ボラをメインに狙うのであれば吸い込み仕掛けが有効です。団子状にした練りエサに針を埋め込み、ボラに食べさせる仕掛けです。鯉は簡単に釣れますが、ボラは狙うと釣れにくい傾向にあります。. 4.**ハゼ**：年によって釣れ始める時期が異なります。早ければ6月の前半、遅ければ6月の後半頃から釣れ始める傾向にあります。ただ、この時期は数は釣れてもサイズが小さい場合があります。もう少し成長してから狙う方がよさそうですが、釣りたい場合はかなり小さい針で狙いに行く必要があります。時間帯は朝・夕のマズメ時が良さそうですが、少しずつ日中でも釣れるようになる傾向にあります。. 5.**ヒラメ**：この時期は、ヒラメの産卵時期にあたるため浅場で捕食する時期とされます。このポイントでも多くはありませんが、チャンスはありそうです。一般的には大物が出やすい時期ではありますが、過去のデータより、このポイントでは30～40cm級にとどまる可能性が高そうです。釣り方はルアーで狙われることが多い魚種となります。. 6.**エイ**：ときどき釣れることがあります。釣りあげた際には尾の付け根に毒の棘がありますので、素手では触らないようにご注意ください。かなり引きが強く、筆者は釣りあげるのを諦めることが多い魚です。ただ、大切なルアーや仕掛けを回収するために頑張ることもありますが、最後にはラインが切れる場合や、疲れて諦めてしまう場合があります。. ## 🏕️ 安心の周辺施設・設備チェック. 木曽川河口周辺のトイレ、駐車場、コンビニ、釣具店、食事処、お土産、宿泊など、釣行前に確認しておきたい設備情報をまとめています。. ## 🗺️ Googleマップを見る｜木曽川河口（まずはカギを）. 住所：〒511-1112 三重県桑名市長島町大倉17-52. ## 🗝️ 国土交通省河川事務所　長島出張所でカギをかりる. 営業日は平日のみ9:00～12:00，13:00～16:30. 7月の調査時の「国土交通省木曽川下流河川事務所　長島出張所」です。堤防沿いにあり、草が茂っているため入り口はやや分かりにくいので注意して下さい。. ## 📸 現地のようす（写真）｜木曽川河口. 木曽川河口では有名な釣り場「円盤」です。足場は良いですが、根がかりしやすい方向があるため注意が必要。7月の調査時は釣り人はいませんでした。. 釣行・駐車・立ち入りは、必ず現地のルール・交通法規を優先してください。. ### 🎣 近隣の釣り場4選（四日市）. Copyright © 釣りに行こう～三重釣り情報～ All Rights Reserved. Powered by WordPress &  Lightning Theme by Vektor,Inc. technology."},{"title":"【木曽川2020】シーバスゲーム攻略法 釣れるルアー＆釣り方を解説","url":"https://www.excite.co.jp/news/article/Tsurinews_tsurinews110712","snippet":"干潮間際や風が強いときなどは、どうしても水が濁ってくる。そんなときは赤金系のルアーがお勧め。この3色は確実にルアーケースに入れておいてほしい。"},{"title":"ルアーのカラーについて質問です。私は青系や緑系の鮮やかな色が好き... - Yahoo!知恵袋","url":"https://detail.chiebukuro.yahoo.co.jp/qa/question_detail/q12227536712","snippet":"# ルアーのカラーについて質問です。 私は青系や緑系の鮮やかな色が好きで気がつけば持っているルアーは7割ほどナチュラルカラー？になってしまいました。 赤系やチャート系も持ってはいますが投げる気になれず投げても すぐ変えるか使わない事が多いです。 やはり釣果を出すためにはカラーは気にした方がいいのでしょうか？ ルアーも安くはないので出来れば気に入った物を買いたいのですが…やっぱり魚も釣りたいので… 色々な意見が聞ければ嬉しいです。. ## 回答（6件）. ルアーフィッシングって、まずはルアー 自体が自信を持って投げられる色形してないとね。 個人的にはこんな色や形の魚は居ないって言うルアーが好きですけど。 色んな考え方があって良いし、自分がこれで釣りたいって言うルアーを投げて釣った方が楽しいでしょ。 私はあんま気にしなくて良いと思いますよ。. ルアーカラーの質問は、定期的に上がります。 今回の私の回答は、過去に行った回答を、貴方の対象魚がシーバスである前提で修正しました。 「気にすべきか？」については、気にした方が良いでしょう。 ただし、ルアーカラーについては、以下の事が言えます。 まず第一に、人間と魚では、色彩として感知する細胞に違いがあります。 例えば人間には区別できる緑とオレンジの違いも、魚は識別できない可能性が高いです。 逆に、人間には感知できない紫外線を認知します。 そして人間の目は、色の補正を行うし心理的な影響も受けます。 蛍光灯の下で、紙が白く見える現象が色補正です。 （本当は白ではなく青っぽく偏光してます） あるいは、明るい色が膨張して見えるのが心理的影響で、これらの機能が魚にもあるかは不明です。 なにより水中では、色の到達距離が違います。 紫外線が最も遠くまで進み、次いで青、赤が最も到達しません。 深い水中で赤は、赤い波長の光がないので黒になります。 なので陸上で見ている人間と、水中で見ている魚では、モノの見え方が全く違うのです。 ルアーを上から見るか下から見るかでも違いが出ます。 人間がナチュラル系と思っている色も、魚からすれば派手なアピールカラーである可能性もあるのです。 逆に、アピール代表のチャートリュースが、最も自然に見えるのかも知れません。 分かっている事として、魚が銀色に見える色素のグアニンは、アルミの色に近い波長だそうです。 人間の目で見るとメッキの方がリアルに見えますが、魚からはそう見えない可能性が高いのです。 そしてアルミの銀色は、紫外線をよく反射する特性もあります。 定番と呼ばれるカラーもありますが、どこまで通用するかは誰も解明していません。 年間何百匹と釣って研究している、メーカーのルアー開発者ですら解明出来ていません。 解明できていれば、メーカーは「〇〇専用カラー」などと大々的に宣伝するでしょうし、シーバス関連の書籍でも大きく紹介されます。 もはや誰もが知る常識となっていなければ不自然ですし、シーバス用のルアーの色にももっと偏りが出るでしょう。 知恵袋で「色による釣果の差はある」と言う人が時々いますが、どの条件でどの色が優位なのかの法則を、明確に説明した人はいません。 せいぜいが濁りのある時は〇〇、ベイトフィッシュが××な時は△△程度です。 それが絶対的な関係であれば良いのですが、そうとも言い切れないのはメーカー等の現状を見れば自明の理です。 日中はナチュラル系が良いと言われますが、これは日中にナチュラル系を使う人が多いから成果に繋がっていると推察出来ます。 しかし現実には、日中でもチャートリュースの様な、実際のベイトとかけ離れた色でも釣れます。 ルアーの定番カラーであるコンスタンギーゴは、モデルとなる魚すらいません。 私がデイ・ナイト合わせて最も釣れている色は、青銀です。 特にラパラの青銀で、ラパラの銀はアルミを使用しています。 青の可視光線と紫外線の到達距離が長い事を勘案すると、多少は理に適っていると言えます。 その次に釣れているのは、半透明のゴースト系カラーです。 どこかの大学がシーバスの好む餌の色の研究をしたところ、透明が若干優位なものの、ほとんど差が出ないとの結論に達していました。 この実験では、背景色との関係についても追及していたので、実際の状況での比較に極めて近い研究です。 ゴーストカラーは私の二番目ですが、一応この実験結果に合致していて、二番目となっている理由は使用頻度の影響と思います。 誰もが自分の信頼できる色を最も使うので、どうしてもその色の釣果が上がってしまうでしょう。 条件による使い分けでも同じです。 同じ条件で同じ色を使い続ければ、それより少なく使用しているルアーより釣果が上がります。 ですから私の結果の青銀も、「最も使っているから」と推察した方が適切と思います。 以上長々と説明しましたが、結局は「魚の気分次第」である以上の事は言えず、ならば釣り人側も気分次第で選ばざるを得ないでしょう。 何しろ「釣れない気がするルアー」を、長く使い続けるのは苦痛です。. 昔 今江のビデオ。 台風通過後の琵琶湖。 水質境目の琵琶湖大橋下で 爆釣したのが 当時 ティファの ディープショット。 カラーはチャート。 これが 引き金となり ディープショットは プレミア化。(笑) 以来 チャート好きに。 (笑) 後 膨張色と判明。 違和感なく 使ってます。. 魚種や水の色にもよるかな...と。 エリアトラウトなんかは、色、かなり選んで使います。 また、このエリアにはこのカラーが強いってのもあったりしますし、放流まもなくはとにかく目立てばいいって時もあります。 また、メバルの夜釣りなんかでも、同じ場所であっても、その日の状況によって明らかに色による食いの違いを、私は感じます。 バスではたまにこのカラーが連続ヒットなんて事もありますが、基本的にはあまり気にしなくなりました。 ただ、デカいルアーの場合には、なるべく色は地味な物からにしてます。 ボディーのインパクトがあるので。 シーバスについては、完全に好みのカラーに絞って使ってます。 冒険したい時もありますが、私の地域では、個体数が少ないので、なるべく実績のあるカラーから使っています。 ただ、どの釣りでも共通してるのは、釣れてる時ほどルアー(カラー)チェンジする様にしてます。 そうすれば、そのルアー(カラー)が効いてるのかどうかがわかるので。. ルアーの開発時点では、プロたちが透明なルアーで釣りをしていることも多いようですし、ルアーのカラーなんて何でも良いというのが正直なところです。（笑） 私も、昔はアユカラーと金/黒があれば何とかなると思っていました。 今は、中古ルアーを買うことが多くなり、カラーを選べないので、何でも良いと思うようになりました。 ただ、メガバスの赤トラカラーは一度爆釣を味わってから、特別に一軍カラーになっています。. ## カテゴリQ&Aランキング. 女性一人で釣りに行く人って、いますか？私は、ソロキャンプに良く行くのですが、釣りもやってみたいと思っています。3回ほど、川をせき止めてある管理釣り場でニジマスを釣りに行きました。とても楽かったので、また行きたくて仕方ありません。その時は、夫や知り合いと一緒だったのですが、今度は一人で行ってみたいのです。でも、女性のソロキャンプは今では珍しくないですが、女性で一人で釣りに行くのって、あまり聞いた事がありません。若い女性なら、まだいいとして、けっこう年齢の女性だと、変な人と見られるのかなぁ、なんて、考えてしまいます。ちなみに、今年で還暦です。人に迷惑かけなければ、好きにやればいいとは思うので... 先日とてもいやな思いをしました。とある漁港で一人で釣りをしていました。（本人女性）そこへ中年の男性が相次いで二人きました。船で作業していたので、地元の漁師のようです。その二人の男性は私のほうを見てわざと見せつけるように放尿したのです。しかも終わってからも５分以上下半身を出して見せつけていました。距離は少しあったのですが明らかに見せつける感じでした。別にトイレしたいのなら、近くに公衆トイレもあり、海に向かってしなくても堤防向けてすればいいと思います。セクハラだし、猥褻物陳列罪ですよね。自分の職場に放尿もびっくりですがそんな人の捕った魚食べたくないし、出荷前に魚にかけてても不思議じゃない。こ... 釣りにおいて、大きい魚を釣り上げるのは実力もあるとは思うのですが、7割くらいは運だと思ってるのですが、技術なんですか？大きい群れが回ってきてたら大きいのが釣れますし、イサキなんかは棚を上にすると比較的大きいのがかかるイメージです。. 「管理釣り場」を執拗に「釣り堀」と呼びたがる人、あるいは逆に「管理釣り場」は「管理釣り場」と呼ぶ人に質問です。Q1.自然渓流を、石で区間を区切ったマス釣り場があります。例えば奥多摩フィッシングセンターなどです（各地に、同様の管理釣り場は沢山あると思います）。水は常に上流から下流に流れていて、滞留していません。さて、これは「釣り堀」ですか？Q2.各地に、区間を決めた冬季釣り場があります。放流の主体はニジマスで、放流量は、区間外に比べて、非常に多いです。さて、これは「釣り堀」ですか？Q3.各地にキャッチアンドリリース区間が設定されてる川があります。魚が目視できたり、ライズ量やライズの発生率が... 釣りでの自己防衛手段について、皆さんはなどのような事をされてますか？私の場合、自分の命を守るためのライフジャケットは当たり前。また、他人に怪我をさせたり不注意で他人の道具を破損させてしまった事態に備えて損害保険に加入しています。自動車保険に追加するかたちで最高二億。動機としては、私のホームは中国地方の漁港·防波堤では最高峰の存在なので、広島福山倉敷岡山方面からヤカラ、家族連れ、ジジババ軍団などがやって来て、不規則な動きやモノの配置をするから。だから怖く思って加入しました。. SNSに魚を大量に並べて自慢してるやつらは何とかならないのでしょうか？？食べきれないから親戚に配る？笑わせるな。自分で食べきれる分だけで良いだろうが、、、自己満足で、俺はこんなに釣れたんだぞ！！って、、大量のアオリイカ、大量のキジハタ、大量のアジ、食べきれもしない大型の魚。何とかならないのでしょうか？？. ## あなたも答えてみませんか. ファンドリィの柔軟剤を買ってみたのですが、 よく見ると果肉入りジュースのように 白いゴミのようなものが浮いていました。 説明欄や注意書きを見てみたのですが、 そのような表記はありませんでした。 ※見. 探しているハロー！モーニングの動画があります。 イントロクイズのやつです。 たしか、けっこう最後のほうのやつだったかと。 ミキティがブギートレイン'03歌ってたぐらいしか覚えてないです。 情報量... bubble Web版について クレカ登録をしたいのですが、失敗コードがでてきて一生登録できないんです！ どなたかおしえてくださいませ（；\\_；）. アロカシアクプレアについて教えて下さい。 アロカシア初心者です。 1週間前にお迎えしたクプレアの葉裏が溶けてきました。 触るとねちょっとした紫の絵の具みたいなのが指に付きます。 まだ購入時のま... ## 総合Q&Aランキング. 僻地という表現は失礼ですか？今日、ある人(50代くらい)と話す予定がありましてその人に自分の将来のことを説明しなければいけませんでした。そのときに、医師や薬剤師の数が少ない僻地の医療現場で医師または薬剤師として働き、仕事を通して社会に貢献したいという言い方をしたのですが、その返答で「僻地という言い方... 国宝のラストについての見解を お聞かせくださいませ 原作も読み 映画も観ました 面白かったの一言 ただラストを 皆さま どうとらえたか？を 自由にお聞かせ願えたらと思いました よろしくお願いいたします. もっちゅりんについて質問です。 今日もっちゅりんを購入し、翌日友人と食べる予定なのですが冷蔵庫に入れるか、冷房の効いた部屋においておくかで迷っています。この時期はどちら方がいいでしょうか( ; ; )、. ## 質問内容."},{"title":"木曽川シーバス絶好調！雨の濁りで確率UP！ - 釣り情報 - イシグロ","url":"https://www.ishiguro-gr.com/enjoy/fishing/detail.php?id=37011","snippet":"メーカー：メガバスルアー：カゲロウ100F カラー：シークレットデッドスティッキング. 釣行日: 2026/05/10. 釣行時間: 19:00～23:00. 釣場: その他. ポイント. 釣魚: シーバス."}],"collectedAt":"2026-06-08T15:19:24.336Z","usedInKnowledgeIds":[]}],"supportingExperiences":[],"contradictingExperiences":[],"confidenceScore":0.2,"sourceKnowledgeId":null,"tags":[],"folderId":"6a2b6d82362131396b29a425","createdAt":"2026-06-08T15:19:23.564Z","__v":0},{"_id":"6a26dd7be4dae4e20a07e187","field":"釣り","type":"hypothesis","category":"ルアーカラー","subcategory":"","content":"干潮間際や強風による濁りが発生した木曽川では、視認性の高い赤金系のルアーをスローリトリーブで引くことで、シーバスからの反応が増加する。","webSources":[{"field":"釣り","query":"木曽川で反応のいいルアーカラーについて","results":[{"title":"【木曽川2020】シーバスゲーム攻略法 釣れるルアー＆釣り方を解説","url":"https://tsurinews.jp/110712","snippet":"次に赤系が少しでも入っているルアーも、強い反応が得られる。赤系はスローリトリーブをすると、魚の反応がいいため覚えていてほしい。 赤金. 干潮間際や"},{"title":"木曽川河口の釣り場｜ルアー・投げ釣りの人気スポット。駐車スペース・トイレ・空撮マップで確認｜汽水の釣りで成果を出す！","url":"https://turiniikou.com/home/map-mie-kita/map-mie-hokubu/point-kisogawa","snippet":"# 木曽川河口の釣り｜シーバス・マゴチが釣れる！│釣り場情報とマップ. 木曽川河口エリアで釣りをする際に知っておきたい情報を整理しました。現地調査で見てきた堤防・足場の状態や、季節ごとの魚の反応など、現地のありのままの情報になります。地図と一緒に、釣行前のシミュレーション用としてご活用いただければ幸いです。. ## 木曽川河口の釣り場. ## 🛰️ 空から木曽川河口の釣り場をチェック. ### マークしたポイント. ## 🏖️ 釣り場の紹介 | 木曽川河口. ### 木曽川河口の特徴. 過去の岸釣りでの情報からは、シーバスに関しては木曽川河口の方がランカーサイズ（80cm以上）の情報が多く出ており、中には90cm以上の情報が複数あるなど、木曽川河口のポテンシャルの高さを感じさせます。. ちなみに、シーバスには主に3種類の魚種があり、スズキ（マルスズキ）、ヒラスズキ、タイリクスズキが一般的にシーバスと呼ばれます。そして、シーバスの岸（磯も含む）釣りでの日本記録はどれくらいかというと、2006年11月に茨城県涸沼川で釣られたスズキが107cm、9.5㎏の記録があります。. ### 木曽川河口で人気のある魚種. ### 注意すべき情報. ### 過去の代表的な釣果情報. ※　イラスト地図上に ●(青い丸）で示したポイントは通称円盤と言われ足場がよく釣りをしやすい人気のポイントです。ただし、釣りを行う方向によっては根がかりをすることが多いという情報もあります。現地では根がかりに注意しながら釣りを行ってください。. ※この釣り場は堤防下へ車で入ることで釣りやすくなります。駐車場の問題、釣り座への移動の問題が解決し、スムーズに釣りが可能になります。このページの下方に記載している方法でカギをかりると、木曽川河口の南側堤防沿いに数か所ある入り口から中に入ることができます。是非ともご活用ください。. ### 🚩ちなみに、似たような雰囲気の釣り場はこちらもおすすめです：. ### 🚩ちなみに、近隣のマゴチが釣れやすい釣り場はこちらもおすすめです：. ### 🚩ちなみに、近隣のシーバスが釣れやすい釣り場はこちらもおすすめです：. ## 🎣 季節ごとに釣れる魚 | 木曽川河口. ### 春（3月～5月）. ### 夏（6月～8月）. シーバス・マゴチ・ウナギ・クロダイ（キビレを含む）・テナガエビ. ### 秋（9月～11月）. シーバス・マゴチ・クロダイ（キビレを含む）・ヒラメ・ハゼ・ボラ. ### 冬（12月～2月）. ## 📍 当たるか外れるかは別として、4月～6月の注目魚 | 木曽川河口. #### **1.シーバス**. **一般的な4月～6月の特徴**：4月は「バチ抜け」によるナイトゲームが期待できます。5月・6月になるとハク（ボラの稚魚）などの小魚を追うようになり、日中のデイゲームでも活性が高まるとされます。. **当ポイントでの特徴**：例年通りであれば、4月は好調ですが、5月～6月と徐々に釣果は低下傾向にあります。. **釣り方**：ルアー釣り（ワームを含む）が中心となります。電気ウキやブッコミ釣りも効果的です。. **サイズ**：4月は40～50cmが狙えます。6月までは50cm級も狙えますが、20～30cmの小型が増える傾向にあります。掲載時点の4月はランカーサイズ（80cm以上）の情報があり、期待できるシーズンです。. **一般的な4月～6月の特徴**：4月から産卵のために浅場へ移動を開始し、5月・6月はハイシーズンに突入します。産卵のために接岸する良型個体をルアーで狙える時期です。. **当ポイントでの特徴**：早い年で4月中旬、例年通りだと4月下旬頃から釣果が上がっていく傾向にあります。過去情報から、このポイントでは春のピークは5月に訪れます。. **サイズ**：サイズは30～50cmが中心で、マーゴン（60cm以上）の情報が複数ある時期になり、期待は高まります。. **時間帯**：朝・夕のマズメ時が中心となりますが、日中でも期待できます。ただし、マーゴン（60cm以上）を狙うのであれば、朝・夕のマズメは外せません。当サイトのデータでは、マーゴン（60cm以上）はマズメ時に実績が多い傾向にあります。. 1.**ウナギ**：5月頃から釣れ出す傾向にあります。例年ですと、6月はさらに釣果が伸びます。土用の丑の日に向けて釣り人も増える傾向にあります。時間帯は基本的には夜間が中心となります。夕マズメ～夜22時頃までが一般的に釣れやすいと言われる時間ですが、筆者も同じような印象です。19時頃に釣れやすいという話をよく聞きますが、筆者は20時～22時が勝負だと思っています。帰って寝たい時間帯ですが、過去の経験上は粘った方が良い時間帯です。ただし、筆者は家族で食べる2～3匹を釣れれば帰る方式をとっています。. 釣り方はぶっこみ釣りが中心となります。エサはドバミミズ、アオイソメ、アケミ貝などいろいろ使われます。筆者はアオイソメをよく使いますが、タイミングによってはセイゴやクロダイ（小）などの外道も多く釣れます。外道も楽しみながら釣りをする場合には有効です。. 2.**クロダイ**：情報は限られていますが、ポツポツ釣れる傾向にあります。サイズはまずまずで45cm級の情報が多く、年なし（50cm以上）の話も聞かれます。釣り方はチニングと言われるルアー釣り（ワームを含む）が多く、シーバスやマゴチとともにルアーで狙うことができます。4月～5月は一般的に乗っ込みと言われる時期で、クロダイの産卵時期にあたり、浅場で捕食することが多くなるとされており、期待が高まる時期です。. 3.**ボラ**：多くはありませんが、釣れることがあります。中には50cm級も釣れるのでタモ網等の装備の準備が必要です。ボラは1日を通して狙える魚で、この場所ではルアー釣りでのスレがかり（口以外に針がかかる）でよく釣れる傾向にあります。もし、ボラをメインに狙うのであれば吸い込み仕掛けが有効です。団子状にした練りエサに針を埋め込み、ボラに食べさせる仕掛けです。鯉は簡単に釣れますが、ボラは狙うと釣れにくい傾向にあります。. 4.**ハゼ**：年によって釣れ始める時期が異なります。早ければ6月の前半、遅ければ6月の後半頃から釣れ始める傾向にあります。ただ、この時期は数は釣れてもサイズが小さい場合があります。もう少し成長してから狙う方がよさそうですが、釣りたい場合はかなり小さい針で狙いに行く必要があります。時間帯は朝・夕のマズメ時が良さそうですが、少しずつ日中でも釣れるようになる傾向にあります。. 5.**ヒラメ**：この時期は、ヒラメの産卵時期にあたるため浅場で捕食する時期とされます。このポイントでも多くはありませんが、チャンスはありそうです。一般的には大物が出やすい時期ではありますが、過去のデータより、このポイントでは30～40cm級にとどまる可能性が高そうです。釣り方はルアーで狙われることが多い魚種となります。. 6.**エイ**：ときどき釣れることがあります。釣りあげた際には尾の付け根に毒の棘がありますので、素手では触らないようにご注意ください。かなり引きが強く、筆者は釣りあげるのを諦めることが多い魚です。ただ、大切なルアーや仕掛けを回収するために頑張ることもありますが、最後にはラインが切れる場合や、疲れて諦めてしまう場合があります。. ## 🏕️ 安心の周辺施設・設備チェック. 木曽川河口周辺のトイレ、駐車場、コンビニ、釣具店、食事処、お土産、宿泊など、釣行前に確認しておきたい設備情報をまとめています。. ## 🗺️ Googleマップを見る｜木曽川河口（まずはカギを）. 住所：〒511-1112 三重県桑名市長島町大倉17-52. ## 🗝️ 国土交通省河川事務所　長島出張所でカギをかりる. 営業日は平日のみ9:00～12:00，13:00～16:30. 7月の調査時の「国土交通省木曽川下流河川事務所　長島出張所」です。堤防沿いにあり、草が茂っているため入り口はやや分かりにくいので注意して下さい。. ## 📸 現地のようす（写真）｜木曽川河口. 木曽川河口では有名な釣り場「円盤」です。足場は良いですが、根がかりしやすい方向があるため注意が必要。7月の調査時は釣り人はいませんでした。. 釣行・駐車・立ち入りは、必ず現地のルール・交通法規を優先してください。. ### 🎣 近隣の釣り場4選（四日市）. Copyright © 釣りに行こう～三重釣り情報～ All Rights Reserved. Powered by WordPress &  Lightning Theme by Vektor,Inc. technology."},{"title":"【木曽川2020】シーバスゲーム攻略法 釣れるルアー＆釣り方を解説","url":"https://www.excite.co.jp/news/article/Tsurinews_tsurinews110712","snippet":"干潮間際や風が強いときなどは、どうしても水が濁ってくる。そんなときは赤金系のルアーがお勧め。この3色は確実にルアーケースに入れておいてほしい。"},{"title":"ルアーのカラーについて質問です。私は青系や緑系の鮮やかな色が好き... - Yahoo!知恵袋","url":"https://detail.chiebukuro.yahoo.co.jp/qa/question_detail/q12227536712","snippet":"# ルアーのカラーについて質問です。 私は青系や緑系の鮮やかな色が好きで気がつけば持っているルアーは7割ほどナチュラルカラー？になってしまいました。 赤系やチャート系も持ってはいますが投げる気になれず投げても すぐ変えるか使わない事が多いです。 やはり釣果を出すためにはカラーは気にした方がいいのでしょうか？ ルアーも安くはないので出来れば気に入った物を買いたいのですが…やっぱり魚も釣りたいので… 色々な意見が聞ければ嬉しいです。. ## 回答（6件）. ルアーフィッシングって、まずはルアー 自体が自信を持って投げられる色形してないとね。 個人的にはこんな色や形の魚は居ないって言うルアーが好きですけど。 色んな考え方があって良いし、自分がこれで釣りたいって言うルアーを投げて釣った方が楽しいでしょ。 私はあんま気にしなくて良いと思いますよ。. ルアーカラーの質問は、定期的に上がります。 今回の私の回答は、過去に行った回答を、貴方の対象魚がシーバスである前提で修正しました。 「気にすべきか？」については、気にした方が良いでしょう。 ただし、ルアーカラーについては、以下の事が言えます。 まず第一に、人間と魚では、色彩として感知する細胞に違いがあります。 例えば人間には区別できる緑とオレンジの違いも、魚は識別できない可能性が高いです。 逆に、人間には感知できない紫外線を認知します。 そして人間の目は、色の補正を行うし心理的な影響も受けます。 蛍光灯の下で、紙が白く見える現象が色補正です。 （本当は白ではなく青っぽく偏光してます） あるいは、明るい色が膨張して見えるのが心理的影響で、これらの機能が魚にもあるかは不明です。 なにより水中では、色の到達距離が違います。 紫外線が最も遠くまで進み、次いで青、赤が最も到達しません。 深い水中で赤は、赤い波長の光がないので黒になります。 なので陸上で見ている人間と、水中で見ている魚では、モノの見え方が全く違うのです。 ルアーを上から見るか下から見るかでも違いが出ます。 人間がナチュラル系と思っている色も、魚からすれば派手なアピールカラーである可能性もあるのです。 逆に、アピール代表のチャートリュースが、最も自然に見えるのかも知れません。 分かっている事として、魚が銀色に見える色素のグアニンは、アルミの色に近い波長だそうです。 人間の目で見るとメッキの方がリアルに見えますが、魚からはそう見えない可能性が高いのです。 そしてアルミの銀色は、紫外線をよく反射する特性もあります。 定番と呼ばれるカラーもありますが、どこまで通用するかは誰も解明していません。 年間何百匹と釣って研究している、メーカーのルアー開発者ですら解明出来ていません。 解明できていれば、メーカーは「〇〇専用カラー」などと大々的に宣伝するでしょうし、シーバス関連の書籍でも大きく紹介されます。 もはや誰もが知る常識となっていなければ不自然ですし、シーバス用のルアーの色にももっと偏りが出るでしょう。 知恵袋で「色による釣果の差はある」と言う人が時々いますが、どの条件でどの色が優位なのかの法則を、明確に説明した人はいません。 せいぜいが濁りのある時は〇〇、ベイトフィッシュが××な時は△△程度です。 それが絶対的な関係であれば良いのですが、そうとも言い切れないのはメーカー等の現状を見れば自明の理です。 日中はナチュラル系が良いと言われますが、これは日中にナチュラル系を使う人が多いから成果に繋がっていると推察出来ます。 しかし現実には、日中でもチャートリュースの様な、実際のベイトとかけ離れた色でも釣れます。 ルアーの定番カラーであるコンスタンギーゴは、モデルとなる魚すらいません。 私がデイ・ナイト合わせて最も釣れている色は、青銀です。 特にラパラの青銀で、ラパラの銀はアルミを使用しています。 青の可視光線と紫外線の到達距離が長い事を勘案すると、多少は理に適っていると言えます。 その次に釣れているのは、半透明のゴースト系カラーです。 どこかの大学がシーバスの好む餌の色の研究をしたところ、透明が若干優位なものの、ほとんど差が出ないとの結論に達していました。 この実験では、背景色との関係についても追及していたので、実際の状況での比較に極めて近い研究です。 ゴーストカラーは私の二番目ですが、一応この実験結果に合致していて、二番目となっている理由は使用頻度の影響と思います。 誰もが自分の信頼できる色を最も使うので、どうしてもその色の釣果が上がってしまうでしょう。 条件による使い分けでも同じです。 同じ条件で同じ色を使い続ければ、それより少なく使用しているルアーより釣果が上がります。 ですから私の結果の青銀も、「最も使っているから」と推察した方が適切と思います。 以上長々と説明しましたが、結局は「魚の気分次第」である以上の事は言えず、ならば釣り人側も気分次第で選ばざるを得ないでしょう。 何しろ「釣れない気がするルアー」を、長く使い続けるのは苦痛です。. 昔 今江のビデオ。 台風通過後の琵琶湖。 水質境目の琵琶湖大橋下で 爆釣したのが 当時 ティファの ディープショット。 カラーはチャート。 これが 引き金となり ディープショットは プレミア化。(笑) 以来 チャート好きに。 (笑) 後 膨張色と判明。 違和感なく 使ってます。. 魚種や水の色にもよるかな...と。 エリアトラウトなんかは、色、かなり選んで使います。 また、このエリアにはこのカラーが強いってのもあったりしますし、放流まもなくはとにかく目立てばいいって時もあります。 また、メバルの夜釣りなんかでも、同じ場所であっても、その日の状況によって明らかに色による食いの違いを、私は感じます。 バスではたまにこのカラーが連続ヒットなんて事もありますが、基本的にはあまり気にしなくなりました。 ただ、デカいルアーの場合には、なるべく色は地味な物からにしてます。 ボディーのインパクトがあるので。 シーバスについては、完全に好みのカラーに絞って使ってます。 冒険したい時もありますが、私の地域では、個体数が少ないので、なるべく実績のあるカラーから使っています。 ただ、どの釣りでも共通してるのは、釣れてる時ほどルアー(カラー)チェンジする様にしてます。 そうすれば、そのルアー(カラー)が効いてるのかどうかがわかるので。. ルアーの開発時点では、プロたちが透明なルアーで釣りをしていることも多いようですし、ルアーのカラーなんて何でも良いというのが正直なところです。（笑） 私も、昔はアユカラーと金/黒があれば何とかなると思っていました。 今は、中古ルアーを買うことが多くなり、カラーを選べないので、何でも良いと思うようになりました。 ただ、メガバスの赤トラカラーは一度爆釣を味わってから、特別に一軍カラーになっています。. ## カテゴリQ&Aランキング. 女性一人で釣りに行く人って、いますか？私は、ソロキャンプに良く行くのですが、釣りもやってみたいと思っています。3回ほど、川をせき止めてある管理釣り場でニジマスを釣りに行きました。とても楽かったので、また行きたくて仕方ありません。その時は、夫や知り合いと一緒だったのですが、今度は一人で行ってみたいのです。でも、女性のソロキャンプは今では珍しくないですが、女性で一人で釣りに行くのって、あまり聞いた事がありません。若い女性なら、まだいいとして、けっこう年齢の女性だと、変な人と見られるのかなぁ、なんて、考えてしまいます。ちなみに、今年で還暦です。人に迷惑かけなければ、好きにやればいいとは思うので... 先日とてもいやな思いをしました。とある漁港で一人で釣りをしていました。（本人女性）そこへ中年の男性が相次いで二人きました。船で作業していたので、地元の漁師のようです。その二人の男性は私のほうを見てわざと見せつけるように放尿したのです。しかも終わってからも５分以上下半身を出して見せつけていました。距離は少しあったのですが明らかに見せつける感じでした。別にトイレしたいのなら、近くに公衆トイレもあり、海に向かってしなくても堤防向けてすればいいと思います。セクハラだし、猥褻物陳列罪ですよね。自分の職場に放尿もびっくりですがそんな人の捕った魚食べたくないし、出荷前に魚にかけてても不思議じゃない。こ... 釣りにおいて、大きい魚を釣り上げるのは実力もあるとは思うのですが、7割くらいは運だと思ってるのですが、技術なんですか？大きい群れが回ってきてたら大きいのが釣れますし、イサキなんかは棚を上にすると比較的大きいのがかかるイメージです。. 「管理釣り場」を執拗に「釣り堀」と呼びたがる人、あるいは逆に「管理釣り場」は「管理釣り場」と呼ぶ人に質問です。Q1.自然渓流を、石で区間を区切ったマス釣り場があります。例えば奥多摩フィッシングセンターなどです（各地に、同様の管理釣り場は沢山あると思います）。水は常に上流から下流に流れていて、滞留していません。さて、これは「釣り堀」ですか？Q2.各地に、区間を決めた冬季釣り場があります。放流の主体はニジマスで、放流量は、区間外に比べて、非常に多いです。さて、これは「釣り堀」ですか？Q3.各地にキャッチアンドリリース区間が設定されてる川があります。魚が目視できたり、ライズ量やライズの発生率が... 釣りでの自己防衛手段について、皆さんはなどのような事をされてますか？私の場合、自分の命を守るためのライフジャケットは当たり前。また、他人に怪我をさせたり不注意で他人の道具を破損させてしまった事態に備えて損害保険に加入しています。自動車保険に追加するかたちで最高二億。動機としては、私のホームは中国地方の漁港·防波堤では最高峰の存在なので、広島福山倉敷岡山方面からヤカラ、家族連れ、ジジババ軍団などがやって来て、不規則な動きやモノの配置をするから。だから怖く思って加入しました。. SNSに魚を大量に並べて自慢してるやつらは何とかならないのでしょうか？？食べきれないから親戚に配る？笑わせるな。自分で食べきれる分だけで良いだろうが、、、自己満足で、俺はこんなに釣れたんだぞ！！って、、大量のアオリイカ、大量のキジハタ、大量のアジ、食べきれもしない大型の魚。何とかならないのでしょうか？？. ## あなたも答えてみませんか. ファンドリィの柔軟剤を買ってみたのですが、 よく見ると果肉入りジュースのように 白いゴミのようなものが浮いていました。 説明欄や注意書きを見てみたのですが、 そのような表記はありませんでした。 ※見. 探しているハロー！モーニングの動画があります。 イントロクイズのやつです。 たしか、けっこう最後のほうのやつだったかと。 ミキティがブギートレイン'03歌ってたぐらいしか覚えてないです。 情報量... bubble Web版について クレカ登録をしたいのですが、失敗コードがでてきて一生登録できないんです！ どなたかおしえてくださいませ（；\\_；）. アロカシアクプレアについて教えて下さい。 アロカシア初心者です。 1週間前にお迎えしたクプレアの葉裏が溶けてきました。 触るとねちょっとした紫の絵の具みたいなのが指に付きます。 まだ購入時のま... ## 総合Q&Aランキング. 僻地という表現は失礼ですか？今日、ある人(50代くらい)と話す予定がありましてその人に自分の将来のことを説明しなければいけませんでした。そのときに、医師や薬剤師の数が少ない僻地の医療現場で医師または薬剤師として働き、仕事を通して社会に貢献したいという言い方をしたのですが、その返答で「僻地という言い方... 国宝のラストについての見解を お聞かせくださいませ 原作も読み 映画も観ました 面白かったの一言 ただラストを 皆さま どうとらえたか？を 自由にお聞かせ願えたらと思いました よろしくお願いいたします. もっちゅりんについて質問です。 今日もっちゅりんを購入し、翌日友人と食べる予定なのですが冷蔵庫に入れるか、冷房の効いた部屋においておくかで迷っています。この時期はどちら方がいいでしょうか( ; ; )、. ## 質問内容."},{"title":"木曽川シーバス絶好調！雨の濁りで確率UP！ - 釣り情報 - イシグロ","url":"https://www.ishiguro-gr.com/enjoy/fishing/detail.php?id=37011","snippet":"メーカー：メガバスルアー：カゲロウ100F カラー：シークレットデッドスティッキング. 釣行日: 2026/05/10. 釣行時間: 19:00～23:00. 釣場: その他. ポイント. 釣魚: シーバス."}],"collectedAt":"2026-06-08T15:19:24.338Z","usedInKnowledgeIds":[]}],"supportingExperiences":[],"contradictingExperiences":[],"confidenceScore":0.2,"sourceKnowledgeId":null,"tags":[],"folderId":"6a2b6d83362131396b29a428","createdAt":"2026-06-08T15:19:23.529Z","__v":0},{"_id":"6a26dd7b51b888e33b7dc229","field":"釣り","type":"hypothesis","category":"ルアーカラー","subcategory":"","content":"日中の光量が多いデイゲームにおいて、紫外線を反射しやすいアルミ仕様の青銀カラーを使用することで、シーバスへのアピール力が高まり釣果が向上する。","webSources":[{"field":"釣り","query":"木曽川で反応のいいルアーカラーについて","results":[{"title":"【木曽川2020】シーバスゲーム攻略法 釣れるルアー＆釣り方を解説","url":"https://tsurinews.jp/110712","snippet":"次に赤系が少しでも入っているルアーも、強い反応が得られる。赤系はスローリトリーブをすると、魚の反応がいいため覚えていてほしい。 赤金. 干潮間際や"},{"title":"木曽川河口の釣り場｜ルアー・投げ釣りの人気スポット。駐車スペース・トイレ・空撮マップで確認｜汽水の釣りで成果を出す！","url":"https://turiniikou.com/home/map-mie-kita/map-mie-hokubu/point-kisogawa","snippet":"# 木曽川河口の釣り｜シーバス・マゴチが釣れる！│釣り場情報とマップ. 木曽川河口エリアで釣りをする際に知っておきたい情報を整理しました。現地調査で見てきた堤防・足場の状態や、季節ごとの魚の反応など、現地のありのままの情報になります。地図と一緒に、釣行前のシミュレーション用としてご活用いただければ幸いです。. ## 木曽川河口の釣り場. ## 🛰️ 空から木曽川河口の釣り場をチェック. ### マークしたポイント. ## 🏖️ 釣り場の紹介 | 木曽川河口. ### 木曽川河口の特徴. 過去の岸釣りでの情報からは、シーバスに関しては木曽川河口の方がランカーサイズ（80cm以上）の情報が多く出ており、中には90cm以上の情報が複数あるなど、木曽川河口のポテンシャルの高さを感じさせます。. ちなみに、シーバスには主に3種類の魚種があり、スズキ（マルスズキ）、ヒラスズキ、タイリクスズキが一般的にシーバスと呼ばれます。そして、シーバスの岸（磯も含む）釣りでの日本記録はどれくらいかというと、2006年11月に茨城県涸沼川で釣られたスズキが107cm、9.5㎏の記録があります。. ### 木曽川河口で人気のある魚種. ### 注意すべき情報. ### 過去の代表的な釣果情報. ※　イラスト地図上に ●(青い丸）で示したポイントは通称円盤と言われ足場がよく釣りをしやすい人気のポイントです。ただし、釣りを行う方向によっては根がかりをすることが多いという情報もあります。現地では根がかりに注意しながら釣りを行ってください。. ※この釣り場は堤防下へ車で入ることで釣りやすくなります。駐車場の問題、釣り座への移動の問題が解決し、スムーズに釣りが可能になります。このページの下方に記載している方法でカギをかりると、木曽川河口の南側堤防沿いに数か所ある入り口から中に入ることができます。是非ともご活用ください。. ### 🚩ちなみに、似たような雰囲気の釣り場はこちらもおすすめです：. ### 🚩ちなみに、近隣のマゴチが釣れやすい釣り場はこちらもおすすめです：. ### 🚩ちなみに、近隣のシーバスが釣れやすい釣り場はこちらもおすすめです：. ## 🎣 季節ごとに釣れる魚 | 木曽川河口. ### 春（3月～5月）. ### 夏（6月～8月）. シーバス・マゴチ・ウナギ・クロダイ（キビレを含む）・テナガエビ. ### 秋（9月～11月）. シーバス・マゴチ・クロダイ（キビレを含む）・ヒラメ・ハゼ・ボラ. ### 冬（12月～2月）. ## 📍 当たるか外れるかは別として、4月～6月の注目魚 | 木曽川河口. #### **1.シーバス**. **一般的な4月～6月の特徴**：4月は「バチ抜け」によるナイトゲームが期待できます。5月・6月になるとハク（ボラの稚魚）などの小魚を追うようになり、日中のデイゲームでも活性が高まるとされます。. **当ポイントでの特徴**：例年通りであれば、4月は好調ですが、5月～6月と徐々に釣果は低下傾向にあります。. **釣り方**：ルアー釣り（ワームを含む）が中心となります。電気ウキやブッコミ釣りも効果的です。. **サイズ**：4月は40～50cmが狙えます。6月までは50cm級も狙えますが、20～30cmの小型が増える傾向にあります。掲載時点の4月はランカーサイズ（80cm以上）の情報があり、期待できるシーズンです。. **一般的な4月～6月の特徴**：4月から産卵のために浅場へ移動を開始し、5月・6月はハイシーズンに突入します。産卵のために接岸する良型個体をルアーで狙える時期です。. **当ポイントでの特徴**：早い年で4月中旬、例年通りだと4月下旬頃から釣果が上がっていく傾向にあります。過去情報から、このポイントでは春のピークは5月に訪れます。. **サイズ**：サイズは30～50cmが中心で、マーゴン（60cm以上）の情報が複数ある時期になり、期待は高まります。. **時間帯**：朝・夕のマズメ時が中心となりますが、日中でも期待できます。ただし、マーゴン（60cm以上）を狙うのであれば、朝・夕のマズメは外せません。当サイトのデータでは、マーゴン（60cm以上）はマズメ時に実績が多い傾向にあります。. 1.**ウナギ**：5月頃から釣れ出す傾向にあります。例年ですと、6月はさらに釣果が伸びます。土用の丑の日に向けて釣り人も増える傾向にあります。時間帯は基本的には夜間が中心となります。夕マズメ～夜22時頃までが一般的に釣れやすいと言われる時間ですが、筆者も同じような印象です。19時頃に釣れやすいという話をよく聞きますが、筆者は20時～22時が勝負だと思っています。帰って寝たい時間帯ですが、過去の経験上は粘った方が良い時間帯です。ただし、筆者は家族で食べる2～3匹を釣れれば帰る方式をとっています。. 釣り方はぶっこみ釣りが中心となります。エサはドバミミズ、アオイソメ、アケミ貝などいろいろ使われます。筆者はアオイソメをよく使いますが、タイミングによってはセイゴやクロダイ（小）などの外道も多く釣れます。外道も楽しみながら釣りをする場合には有効です。. 2.**クロダイ**：情報は限られていますが、ポツポツ釣れる傾向にあります。サイズはまずまずで45cm級の情報が多く、年なし（50cm以上）の話も聞かれます。釣り方はチニングと言われるルアー釣り（ワームを含む）が多く、シーバスやマゴチとともにルアーで狙うことができます。4月～5月は一般的に乗っ込みと言われる時期で、クロダイの産卵時期にあたり、浅場で捕食することが多くなるとされており、期待が高まる時期です。. 3.**ボラ**：多くはありませんが、釣れることがあります。中には50cm級も釣れるのでタモ網等の装備の準備が必要です。ボラは1日を通して狙える魚で、この場所ではルアー釣りでのスレがかり（口以外に針がかかる）でよく釣れる傾向にあります。もし、ボラをメインに狙うのであれば吸い込み仕掛けが有効です。団子状にした練りエサに針を埋め込み、ボラに食べさせる仕掛けです。鯉は簡単に釣れますが、ボラは狙うと釣れにくい傾向にあります。. 4.**ハゼ**：年によって釣れ始める時期が異なります。早ければ6月の前半、遅ければ6月の後半頃から釣れ始める傾向にあります。ただ、この時期は数は釣れてもサイズが小さい場合があります。もう少し成長してから狙う方がよさそうですが、釣りたい場合はかなり小さい針で狙いに行く必要があります。時間帯は朝・夕のマズメ時が良さそうですが、少しずつ日中でも釣れるようになる傾向にあります。. 5.**ヒラメ**：この時期は、ヒラメの産卵時期にあたるため浅場で捕食する時期とされます。このポイントでも多くはありませんが、チャンスはありそうです。一般的には大物が出やすい時期ではありますが、過去のデータより、このポイントでは30～40cm級にとどまる可能性が高そうです。釣り方はルアーで狙われることが多い魚種となります。. 6.**エイ**：ときどき釣れることがあります。釣りあげた際には尾の付け根に毒の棘がありますので、素手では触らないようにご注意ください。かなり引きが強く、筆者は釣りあげるのを諦めることが多い魚です。ただ、大切なルアーや仕掛けを回収するために頑張ることもありますが、最後にはラインが切れる場合や、疲れて諦めてしまう場合があります。. ## 🏕️ 安心の周辺施設・設備チェック. 木曽川河口周辺のトイレ、駐車場、コンビニ、釣具店、食事処、お土産、宿泊など、釣行前に確認しておきたい設備情報をまとめています。. ## 🗺️ Googleマップを見る｜木曽川河口（まずはカギを）. 住所：〒511-1112 三重県桑名市長島町大倉17-52. ## 🗝️ 国土交通省河川事務所　長島出張所でカギをかりる. 営業日は平日のみ9:00～12:00，13:00～16:30. 7月の調査時の「国土交通省木曽川下流河川事務所　長島出張所」です。堤防沿いにあり、草が茂っているため入り口はやや分かりにくいので注意して下さい。. ## 📸 現地のようす（写真）｜木曽川河口. 木曽川河口では有名な釣り場「円盤」です。足場は良いですが、根がかりしやすい方向があるため注意が必要。7月の調査時は釣り人はいませんでした。. 釣行・駐車・立ち入りは、必ず現地のルール・交通法規を優先してください。. ### 🎣 近隣の釣り場4選（四日市）. Copyright © 釣りに行こう～三重釣り情報～ All Rights Reserved. Powered by WordPress &  Lightning Theme by Vektor,Inc. technology."},{"title":"【木曽川2020】シーバスゲーム攻略法 釣れるルアー＆釣り方を解説","url":"https://www.excite.co.jp/news/article/Tsurinews_tsurinews110712","snippet":"干潮間際や風が強いときなどは、どうしても水が濁ってくる。そんなときは赤金系のルアーがお勧め。この3色は確実にルアーケースに入れておいてほしい。"},{"title":"ルアーのカラーについて質問です。私は青系や緑系の鮮やかな色が好き... - Yahoo!知恵袋","url":"https://detail.chiebukuro.yahoo.co.jp/qa/question_detail/q12227536712","snippet":"# ルアーのカラーについて質問です。 私は青系や緑系の鮮やかな色が好きで気がつけば持っているルアーは7割ほどナチュラルカラー？になってしまいました。 赤系やチャート系も持ってはいますが投げる気になれず投げても すぐ変えるか使わない事が多いです。 やはり釣果を出すためにはカラーは気にした方がいいのでしょうか？ ルアーも安くはないので出来れば気に入った物を買いたいのですが…やっぱり魚も釣りたいので… 色々な意見が聞ければ嬉しいです。. ## 回答（6件）. ルアーフィッシングって、まずはルアー 自体が自信を持って投げられる色形してないとね。 個人的にはこんな色や形の魚は居ないって言うルアーが好きですけど。 色んな考え方があって良いし、自分がこれで釣りたいって言うルアーを投げて釣った方が楽しいでしょ。 私はあんま気にしなくて良いと思いますよ。. ルアーカラーの質問は、定期的に上がります。 今回の私の回答は、過去に行った回答を、貴方の対象魚がシーバスである前提で修正しました。 「気にすべきか？」については、気にした方が良いでしょう。 ただし、ルアーカラーについては、以下の事が言えます。 まず第一に、人間と魚では、色彩として感知する細胞に違いがあります。 例えば人間には区別できる緑とオレンジの違いも、魚は識別できない可能性が高いです。 逆に、人間には感知できない紫外線を認知します。 そして人間の目は、色の補正を行うし心理的な影響も受けます。 蛍光灯の下で、紙が白く見える現象が色補正です。 （本当は白ではなく青っぽく偏光してます） あるいは、明るい色が膨張して見えるのが心理的影響で、これらの機能が魚にもあるかは不明です。 なにより水中では、色の到達距離が違います。 紫外線が最も遠くまで進み、次いで青、赤が最も到達しません。 深い水中で赤は、赤い波長の光がないので黒になります。 なので陸上で見ている人間と、水中で見ている魚では、モノの見え方が全く違うのです。 ルアーを上から見るか下から見るかでも違いが出ます。 人間がナチュラル系と思っている色も、魚からすれば派手なアピールカラーである可能性もあるのです。 逆に、アピール代表のチャートリュースが、最も自然に見えるのかも知れません。 分かっている事として、魚が銀色に見える色素のグアニンは、アルミの色に近い波長だそうです。 人間の目で見るとメッキの方がリアルに見えますが、魚からはそう見えない可能性が高いのです。 そしてアルミの銀色は、紫外線をよく反射する特性もあります。 定番と呼ばれるカラーもありますが、どこまで通用するかは誰も解明していません。 年間何百匹と釣って研究している、メーカーのルアー開発者ですら解明出来ていません。 解明できていれば、メーカーは「〇〇専用カラー」などと大々的に宣伝するでしょうし、シーバス関連の書籍でも大きく紹介されます。 もはや誰もが知る常識となっていなければ不自然ですし、シーバス用のルアーの色にももっと偏りが出るでしょう。 知恵袋で「色による釣果の差はある」と言う人が時々いますが、どの条件でどの色が優位なのかの法則を、明確に説明した人はいません。 せいぜいが濁りのある時は〇〇、ベイトフィッシュが××な時は△△程度です。 それが絶対的な関係であれば良いのですが、そうとも言い切れないのはメーカー等の現状を見れば自明の理です。 日中はナチュラル系が良いと言われますが、これは日中にナチュラル系を使う人が多いから成果に繋がっていると推察出来ます。 しかし現実には、日中でもチャートリュースの様な、実際のベイトとかけ離れた色でも釣れます。 ルアーの定番カラーであるコンスタンギーゴは、モデルとなる魚すらいません。 私がデイ・ナイト合わせて最も釣れている色は、青銀です。 特にラパラの青銀で、ラパラの銀はアルミを使用しています。 青の可視光線と紫外線の到達距離が長い事を勘案すると、多少は理に適っていると言えます。 その次に釣れているのは、半透明のゴースト系カラーです。 どこかの大学がシーバスの好む餌の色の研究をしたところ、透明が若干優位なものの、ほとんど差が出ないとの結論に達していました。 この実験では、背景色との関係についても追及していたので、実際の状況での比較に極めて近い研究です。 ゴーストカラーは私の二番目ですが、一応この実験結果に合致していて、二番目となっている理由は使用頻度の影響と思います。 誰もが自分の信頼できる色を最も使うので、どうしてもその色の釣果が上がってしまうでしょう。 条件による使い分けでも同じです。 同じ条件で同じ色を使い続ければ、それより少なく使用しているルアーより釣果が上がります。 ですから私の結果の青銀も、「最も使っているから」と推察した方が適切と思います。 以上長々と説明しましたが、結局は「魚の気分次第」である以上の事は言えず、ならば釣り人側も気分次第で選ばざるを得ないでしょう。 何しろ「釣れない気がするルアー」を、長く使い続けるのは苦痛です。. 昔 今江のビデオ。 台風通過後の琵琶湖。 水質境目の琵琶湖大橋下で 爆釣したのが 当時 ティファの ディープショット。 カラーはチャート。 これが 引き金となり ディープショットは プレミア化。(笑) 以来 チャート好きに。 (笑) 後 膨張色と判明。 違和感なく 使ってます。. 魚種や水の色にもよるかな...と。 エリアトラウトなんかは、色、かなり選んで使います。 また、このエリアにはこのカラーが強いってのもあったりしますし、放流まもなくはとにかく目立てばいいって時もあります。 また、メバルの夜釣りなんかでも、同じ場所であっても、その日の状況によって明らかに色による食いの違いを、私は感じます。 バスではたまにこのカラーが連続ヒットなんて事もありますが、基本的にはあまり気にしなくなりました。 ただ、デカいルアーの場合には、なるべく色は地味な物からにしてます。 ボディーのインパクトがあるので。 シーバスについては、完全に好みのカラーに絞って使ってます。 冒険したい時もありますが、私の地域では、個体数が少ないので、なるべく実績のあるカラーから使っています。 ただ、どの釣りでも共通してるのは、釣れてる時ほどルアー(カラー)チェンジする様にしてます。 そうすれば、そのルアー(カラー)が効いてるのかどうかがわかるので。. ルアーの開発時点では、プロたちが透明なルアーで釣りをしていることも多いようですし、ルアーのカラーなんて何でも良いというのが正直なところです。（笑） 私も、昔はアユカラーと金/黒があれば何とかなると思っていました。 今は、中古ルアーを買うことが多くなり、カラーを選べないので、何でも良いと思うようになりました。 ただ、メガバスの赤トラカラーは一度爆釣を味わってから、特別に一軍カラーになっています。. ## カテゴリQ&Aランキング. 女性一人で釣りに行く人って、いますか？私は、ソロキャンプに良く行くのですが、釣りもやってみたいと思っています。3回ほど、川をせき止めてある管理釣り場でニジマスを釣りに行きました。とても楽かったので、また行きたくて仕方ありません。その時は、夫や知り合いと一緒だったのですが、今度は一人で行ってみたいのです。でも、女性のソロキャンプは今では珍しくないですが、女性で一人で釣りに行くのって、あまり聞いた事がありません。若い女性なら、まだいいとして、けっこう年齢の女性だと、変な人と見られるのかなぁ、なんて、考えてしまいます。ちなみに、今年で還暦です。人に迷惑かけなければ、好きにやればいいとは思うので... 先日とてもいやな思いをしました。とある漁港で一人で釣りをしていました。（本人女性）そこへ中年の男性が相次いで二人きました。船で作業していたので、地元の漁師のようです。その二人の男性は私のほうを見てわざと見せつけるように放尿したのです。しかも終わってからも５分以上下半身を出して見せつけていました。距離は少しあったのですが明らかに見せつける感じでした。別にトイレしたいのなら、近くに公衆トイレもあり、海に向かってしなくても堤防向けてすればいいと思います。セクハラだし、猥褻物陳列罪ですよね。自分の職場に放尿もびっくりですがそんな人の捕った魚食べたくないし、出荷前に魚にかけてても不思議じゃない。こ... 釣りにおいて、大きい魚を釣り上げるのは実力もあるとは思うのですが、7割くらいは運だと思ってるのですが、技術なんですか？大きい群れが回ってきてたら大きいのが釣れますし、イサキなんかは棚を上にすると比較的大きいのがかかるイメージです。. 「管理釣り場」を執拗に「釣り堀」と呼びたがる人、あるいは逆に「管理釣り場」は「管理釣り場」と呼ぶ人に質問です。Q1.自然渓流を、石で区間を区切ったマス釣り場があります。例えば奥多摩フィッシングセンターなどです（各地に、同様の管理釣り場は沢山あると思います）。水は常に上流から下流に流れていて、滞留していません。さて、これは「釣り堀」ですか？Q2.各地に、区間を決めた冬季釣り場があります。放流の主体はニジマスで、放流量は、区間外に比べて、非常に多いです。さて、これは「釣り堀」ですか？Q3.各地にキャッチアンドリリース区間が設定されてる川があります。魚が目視できたり、ライズ量やライズの発生率が... 釣りでの自己防衛手段について、皆さんはなどのような事をされてますか？私の場合、自分の命を守るためのライフジャケットは当たり前。また、他人に怪我をさせたり不注意で他人の道具を破損させてしまった事態に備えて損害保険に加入しています。自動車保険に追加するかたちで最高二億。動機としては、私のホームは中国地方の漁港·防波堤では最高峰の存在なので、広島福山倉敷岡山方面からヤカラ、家族連れ、ジジババ軍団などがやって来て、不規則な動きやモノの配置をするから。だから怖く思って加入しました。. SNSに魚を大量に並べて自慢してるやつらは何とかならないのでしょうか？？食べきれないから親戚に配る？笑わせるな。自分で食べきれる分だけで良いだろうが、、、自己満足で、俺はこんなに釣れたんだぞ！！って、、大量のアオリイカ、大量のキジハタ、大量のアジ、食べきれもしない大型の魚。何とかならないのでしょうか？？. ## あなたも答えてみませんか. ファンドリィの柔軟剤を買ってみたのですが、 よく見ると果肉入りジュースのように 白いゴミのようなものが浮いていました。 説明欄や注意書きを見てみたのですが、 そのような表記はありませんでした。 ※見. 探しているハロー！モーニングの動画があります。 イントロクイズのやつです。 たしか、けっこう最後のほうのやつだったかと。 ミキティがブギートレイン'03歌ってたぐらいしか覚えてないです。 情報量... bubble Web版について クレカ登録をしたいのですが、失敗コードがでてきて一生登録できないんです！ どなたかおしえてくださいませ（；\\_；）. アロカシアクプレアについて教えて下さい。 アロカシア初心者です。 1週間前にお迎えしたクプレアの葉裏が溶けてきました。 触るとねちょっとした紫の絵の具みたいなのが指に付きます。 まだ購入時のま... ## 総合Q&Aランキング. 僻地という表現は失礼ですか？今日、ある人(50代くらい)と話す予定がありましてその人に自分の将来のことを説明しなければいけませんでした。そのときに、医師や薬剤師の数が少ない僻地の医療現場で医師または薬剤師として働き、仕事を通して社会に貢献したいという言い方をしたのですが、その返答で「僻地という言い方... 国宝のラストについての見解を お聞かせくださいませ 原作も読み 映画も観ました 面白かったの一言 ただラストを 皆さま どうとらえたか？を 自由にお聞かせ願えたらと思いました よろしくお願いいたします. もっちゅりんについて質問です。 今日もっちゅりんを購入し、翌日友人と食べる予定なのですが冷蔵庫に入れるか、冷房の効いた部屋においておくかで迷っています。この時期はどちら方がいいでしょうか( ; ; )、. ## 質問内容."},{"title":"木曽川シーバス絶好調！雨の濁りで確率UP！ - 釣り情報 - イシグロ","url":"https://www.ishiguro-gr.com/enjoy/fishing/detail.php?id=37011","snippet":"メーカー：メガバスルアー：カゲロウ100F カラー：シークレットデッドスティッキング. 釣行日: 2026/05/10. 釣行時間: 19:00～23:00. 釣場: その他. ポイント. 釣魚: シーバス."}],"collectedAt":"2026-06-08T15:19:24.337Z","usedInKnowledgeIds":[]}],"supportingExperiences":[],"contradictingExperiences":[],"confidenceScore":0.2,"sourceKnowledgeId":null,"tags":[],"folderId":"6a2b6d85362131396b29a42b","createdAt":"2026-06-08T15:19:23.497Z","__v":0},{"_id":"6a26dd7b51b888e33b7dc227","field":"釣り","type":"hypothesis","category":"ルアーカラー","subcategory":"","content":"雨による急な濁りが発生した状況では、チャート系などの膨張色や反射を抑えたカラーのルアーを使用することで、視界の悪い中でもシーバスに効果的にアピールできる。","webSources":[{"field":"釣り","query":"木曽川で反応のいいルアーカラーについて","results":[{"title":"【木曽川2020】シーバスゲーム攻略法 釣れるルアー＆釣り方を解説","url":"https://tsurinews.jp/110712","snippet":"次に赤系が少しでも入っているルアーも、強い反応が得られる。赤系はスローリトリーブをすると、魚の反応がいいため覚えていてほしい。 赤金. 干潮間際や"},{"title":"木曽川河口の釣り場｜ルアー・投げ釣りの人気スポット。駐車スペース・トイレ・空撮マップで確認｜汽水の釣りで成果を出す！","url":"https://turiniikou.com/home/map-mie-kita/map-mie-hokubu/point-kisogawa","snippet":"# 木曽川河口の釣り｜シーバス・マゴチが釣れる！│釣り場情報とマップ. 木曽川河口エリアで釣りをする際に知っておきたい情報を整理しました。現地調査で見てきた堤防・足場の状態や、季節ごとの魚の反応など、現地のありのままの情報になります。地図と一緒に、釣行前のシミュレーション用としてご活用いただければ幸いです。. ## 木曽川河口の釣り場. ## 🛰️ 空から木曽川河口の釣り場をチェック. ### マークしたポイント. ## 🏖️ 釣り場の紹介 | 木曽川河口. ### 木曽川河口の特徴. 過去の岸釣りでの情報からは、シーバスに関しては木曽川河口の方がランカーサイズ（80cm以上）の情報が多く出ており、中には90cm以上の情報が複数あるなど、木曽川河口のポテンシャルの高さを感じさせます。. ちなみに、シーバスには主に3種類の魚種があり、スズキ（マルスズキ）、ヒラスズキ、タイリクスズキが一般的にシーバスと呼ばれます。そして、シーバスの岸（磯も含む）釣りでの日本記録はどれくらいかというと、2006年11月に茨城県涸沼川で釣られたスズキが107cm、9.5㎏の記録があります。. ### 木曽川河口で人気のある魚種. ### 注意すべき情報. ### 過去の代表的な釣果情報. ※　イラスト地図上に ●(青い丸）で示したポイントは通称円盤と言われ足場がよく釣りをしやすい人気のポイントです。ただし、釣りを行う方向によっては根がかりをすることが多いという情報もあります。現地では根がかりに注意しながら釣りを行ってください。. ※この釣り場は堤防下へ車で入ることで釣りやすくなります。駐車場の問題、釣り座への移動の問題が解決し、スムーズに釣りが可能になります。このページの下方に記載している方法でカギをかりると、木曽川河口の南側堤防沿いに数か所ある入り口から中に入ることができます。是非ともご活用ください。. ### 🚩ちなみに、似たような雰囲気の釣り場はこちらもおすすめです：. ### 🚩ちなみに、近隣のマゴチが釣れやすい釣り場はこちらもおすすめです：. ### 🚩ちなみに、近隣のシーバスが釣れやすい釣り場はこちらもおすすめです：. ## 🎣 季節ごとに釣れる魚 | 木曽川河口. ### 春（3月～5月）. ### 夏（6月～8月）. シーバス・マゴチ・ウナギ・クロダイ（キビレを含む）・テナガエビ. ### 秋（9月～11月）. シーバス・マゴチ・クロダイ（キビレを含む）・ヒラメ・ハゼ・ボラ. ### 冬（12月～2月）. ## 📍 当たるか外れるかは別として、4月～6月の注目魚 | 木曽川河口. #### **1.シーバス**. **一般的な4月～6月の特徴**：4月は「バチ抜け」によるナイトゲームが期待できます。5月・6月になるとハク（ボラの稚魚）などの小魚を追うようになり、日中のデイゲームでも活性が高まるとされます。. **当ポイントでの特徴**：例年通りであれば、4月は好調ですが、5月～6月と徐々に釣果は低下傾向にあります。. **釣り方**：ルアー釣り（ワームを含む）が中心となります。電気ウキやブッコミ釣りも効果的です。. **サイズ**：4月は40～50cmが狙えます。6月までは50cm級も狙えますが、20～30cmの小型が増える傾向にあります。掲載時点の4月はランカーサイズ（80cm以上）の情報があり、期待できるシーズンです。. **一般的な4月～6月の特徴**：4月から産卵のために浅場へ移動を開始し、5月・6月はハイシーズンに突入します。産卵のために接岸する良型個体をルアーで狙える時期です。. **当ポイントでの特徴**：早い年で4月中旬、例年通りだと4月下旬頃から釣果が上がっていく傾向にあります。過去情報から、このポイントでは春のピークは5月に訪れます。. **サイズ**：サイズは30～50cmが中心で、マーゴン（60cm以上）の情報が複数ある時期になり、期待は高まります。. **時間帯**：朝・夕のマズメ時が中心となりますが、日中でも期待できます。ただし、マーゴン（60cm以上）を狙うのであれば、朝・夕のマズメは外せません。当サイトのデータでは、マーゴン（60cm以上）はマズメ時に実績が多い傾向にあります。. 1.**ウナギ**：5月頃から釣れ出す傾向にあります。例年ですと、6月はさらに釣果が伸びます。土用の丑の日に向けて釣り人も増える傾向にあります。時間帯は基本的には夜間が中心となります。夕マズメ～夜22時頃までが一般的に釣れやすいと言われる時間ですが、筆者も同じような印象です。19時頃に釣れやすいという話をよく聞きますが、筆者は20時～22時が勝負だと思っています。帰って寝たい時間帯ですが、過去の経験上は粘った方が良い時間帯です。ただし、筆者は家族で食べる2～3匹を釣れれば帰る方式をとっています。. 釣り方はぶっこみ釣りが中心となります。エサはドバミミズ、アオイソメ、アケミ貝などいろいろ使われます。筆者はアオイソメをよく使いますが、タイミングによってはセイゴやクロダイ（小）などの外道も多く釣れます。外道も楽しみながら釣りをする場合には有効です。. 2.**クロダイ**：情報は限られていますが、ポツポツ釣れる傾向にあります。サイズはまずまずで45cm級の情報が多く、年なし（50cm以上）の話も聞かれます。釣り方はチニングと言われるルアー釣り（ワームを含む）が多く、シーバスやマゴチとともにルアーで狙うことができます。4月～5月は一般的に乗っ込みと言われる時期で、クロダイの産卵時期にあたり、浅場で捕食することが多くなるとされており、期待が高まる時期です。. 3.**ボラ**：多くはありませんが、釣れることがあります。中には50cm級も釣れるのでタモ網等の装備の準備が必要です。ボラは1日を通して狙える魚で、この場所ではルアー釣りでのスレがかり（口以外に針がかかる）でよく釣れる傾向にあります。もし、ボラをメインに狙うのであれば吸い込み仕掛けが有効です。団子状にした練りエサに針を埋め込み、ボラに食べさせる仕掛けです。鯉は簡単に釣れますが、ボラは狙うと釣れにくい傾向にあります。. 4.**ハゼ**：年によって釣れ始める時期が異なります。早ければ6月の前半、遅ければ6月の後半頃から釣れ始める傾向にあります。ただ、この時期は数は釣れてもサイズが小さい場合があります。もう少し成長してから狙う方がよさそうですが、釣りたい場合はかなり小さい針で狙いに行く必要があります。時間帯は朝・夕のマズメ時が良さそうですが、少しずつ日中でも釣れるようになる傾向にあります。. 5.**ヒラメ**：この時期は、ヒラメの産卵時期にあたるため浅場で捕食する時期とされます。このポイントでも多くはありませんが、チャンスはありそうです。一般的には大物が出やすい時期ではありますが、過去のデータより、このポイントでは30～40cm級にとどまる可能性が高そうです。釣り方はルアーで狙われることが多い魚種となります。. 6.**エイ**：ときどき釣れることがあります。釣りあげた際には尾の付け根に毒の棘がありますので、素手では触らないようにご注意ください。かなり引きが強く、筆者は釣りあげるのを諦めることが多い魚です。ただ、大切なルアーや仕掛けを回収するために頑張ることもありますが、最後にはラインが切れる場合や、疲れて諦めてしまう場合があります。. ## 🏕️ 安心の周辺施設・設備チェック. 木曽川河口周辺のトイレ、駐車場、コンビニ、釣具店、食事処、お土産、宿泊など、釣行前に確認しておきたい設備情報をまとめています。. ## 🗺️ Googleマップを見る｜木曽川河口（まずはカギを）. 住所：〒511-1112 三重県桑名市長島町大倉17-52. ## 🗝️ 国土交通省河川事務所　長島出張所でカギをかりる. 営業日は平日のみ9:00～12:00，13:00～16:30. 7月の調査時の「国土交通省木曽川下流河川事務所　長島出張所」です。堤防沿いにあり、草が茂っているため入り口はやや分かりにくいので注意して下さい。. ## 📸 現地のようす（写真）｜木曽川河口. 木曽川河口では有名な釣り場「円盤」です。足場は良いですが、根がかりしやすい方向があるため注意が必要。7月の調査時は釣り人はいませんでした。. 釣行・駐車・立ち入りは、必ず現地のルール・交通法規を優先してください。. ### 🎣 近隣の釣り場4選（四日市）. Copyright © 釣りに行こう～三重釣り情報～ All Rights Reserved. Powered by WordPress &  Lightning Theme by Vektor,Inc. technology."},{"title":"【木曽川2020】シーバスゲーム攻略法 釣れるルアー＆釣り方を解説","url":"https://www.excite.co.jp/news/article/Tsurinews_tsurinews110712","snippet":"干潮間際や風が強いときなどは、どうしても水が濁ってくる。そんなときは赤金系のルアーがお勧め。この3色は確実にルアーケースに入れておいてほしい。"},{"title":"ルアーのカラーについて質問です。私は青系や緑系の鮮やかな色が好き... - Yahoo!知恵袋","url":"https://detail.chiebukuro.yahoo.co.jp/qa/question_detail/q12227536712","snippet":"# ルアーのカラーについて質問です。 私は青系や緑系の鮮やかな色が好きで気がつけば持っているルアーは7割ほどナチュラルカラー？になってしまいました。 赤系やチャート系も持ってはいますが投げる気になれず投げても すぐ変えるか使わない事が多いです。 やはり釣果を出すためにはカラーは気にした方がいいのでしょうか？ ルアーも安くはないので出来れば気に入った物を買いたいのですが…やっぱり魚も釣りたいので… 色々な意見が聞ければ嬉しいです。. ## 回答（6件）. ルアーフィッシングって、まずはルアー 自体が自信を持って投げられる色形してないとね。 個人的にはこんな色や形の魚は居ないって言うルアーが好きですけど。 色んな考え方があって良いし、自分がこれで釣りたいって言うルアーを投げて釣った方が楽しいでしょ。 私はあんま気にしなくて良いと思いますよ。. ルアーカラーの質問は、定期的に上がります。 今回の私の回答は、過去に行った回答を、貴方の対象魚がシーバスである前提で修正しました。 「気にすべきか？」については、気にした方が良いでしょう。 ただし、ルアーカラーについては、以下の事が言えます。 まず第一に、人間と魚では、色彩として感知する細胞に違いがあります。 例えば人間には区別できる緑とオレンジの違いも、魚は識別できない可能性が高いです。 逆に、人間には感知できない紫外線を認知します。 そして人間の目は、色の補正を行うし心理的な影響も受けます。 蛍光灯の下で、紙が白く見える現象が色補正です。 （本当は白ではなく青っぽく偏光してます） あるいは、明るい色が膨張して見えるのが心理的影響で、これらの機能が魚にもあるかは不明です。 なにより水中では、色の到達距離が違います。 紫外線が最も遠くまで進み、次いで青、赤が最も到達しません。 深い水中で赤は、赤い波長の光がないので黒になります。 なので陸上で見ている人間と、水中で見ている魚では、モノの見え方が全く違うのです。 ルアーを上から見るか下から見るかでも違いが出ます。 人間がナチュラル系と思っている色も、魚からすれば派手なアピールカラーである可能性もあるのです。 逆に、アピール代表のチャートリュースが、最も自然に見えるのかも知れません。 分かっている事として、魚が銀色に見える色素のグアニンは、アルミの色に近い波長だそうです。 人間の目で見るとメッキの方がリアルに見えますが、魚からはそう見えない可能性が高いのです。 そしてアルミの銀色は、紫外線をよく反射する特性もあります。 定番と呼ばれるカラーもありますが、どこまで通用するかは誰も解明していません。 年間何百匹と釣って研究している、メーカーのルアー開発者ですら解明出来ていません。 解明できていれば、メーカーは「〇〇専用カラー」などと大々的に宣伝するでしょうし、シーバス関連の書籍でも大きく紹介されます。 もはや誰もが知る常識となっていなければ不自然ですし、シーバス用のルアーの色にももっと偏りが出るでしょう。 知恵袋で「色による釣果の差はある」と言う人が時々いますが、どの条件でどの色が優位なのかの法則を、明確に説明した人はいません。 せいぜいが濁りのある時は〇〇、ベイトフィッシュが××な時は△△程度です。 それが絶対的な関係であれば良いのですが、そうとも言い切れないのはメーカー等の現状を見れば自明の理です。 日中はナチュラル系が良いと言われますが、これは日中にナチュラル系を使う人が多いから成果に繋がっていると推察出来ます。 しかし現実には、日中でもチャートリュースの様な、実際のベイトとかけ離れた色でも釣れます。 ルアーの定番カラーであるコンスタンギーゴは、モデルとなる魚すらいません。 私がデイ・ナイト合わせて最も釣れている色は、青銀です。 特にラパラの青銀で、ラパラの銀はアルミを使用しています。 青の可視光線と紫外線の到達距離が長い事を勘案すると、多少は理に適っていると言えます。 その次に釣れているのは、半透明のゴースト系カラーです。 どこかの大学がシーバスの好む餌の色の研究をしたところ、透明が若干優位なものの、ほとんど差が出ないとの結論に達していました。 この実験では、背景色との関係についても追及していたので、実際の状況での比較に極めて近い研究です。 ゴーストカラーは私の二番目ですが、一応この実験結果に合致していて、二番目となっている理由は使用頻度の影響と思います。 誰もが自分の信頼できる色を最も使うので、どうしてもその色の釣果が上がってしまうでしょう。 条件による使い分けでも同じです。 同じ条件で同じ色を使い続ければ、それより少なく使用しているルアーより釣果が上がります。 ですから私の結果の青銀も、「最も使っているから」と推察した方が適切と思います。 以上長々と説明しましたが、結局は「魚の気分次第」である以上の事は言えず、ならば釣り人側も気分次第で選ばざるを得ないでしょう。 何しろ「釣れない気がするルアー」を、長く使い続けるのは苦痛です。. 昔 今江のビデオ。 台風通過後の琵琶湖。 水質境目の琵琶湖大橋下で 爆釣したのが 当時 ティファの ディープショット。 カラーはチャート。 これが 引き金となり ディープショットは プレミア化。(笑) 以来 チャート好きに。 (笑) 後 膨張色と判明。 違和感なく 使ってます。. 魚種や水の色にもよるかな...と。 エリアトラウトなんかは、色、かなり選んで使います。 また、このエリアにはこのカラーが強いってのもあったりしますし、放流まもなくはとにかく目立てばいいって時もあります。 また、メバルの夜釣りなんかでも、同じ場所であっても、その日の状況によって明らかに色による食いの違いを、私は感じます。 バスではたまにこのカラーが連続ヒットなんて事もありますが、基本的にはあまり気にしなくなりました。 ただ、デカいルアーの場合には、なるべく色は地味な物からにしてます。 ボディーのインパクトがあるので。 シーバスについては、完全に好みのカラーに絞って使ってます。 冒険したい時もありますが、私の地域では、個体数が少ないので、なるべく実績のあるカラーから使っています。 ただ、どの釣りでも共通してるのは、釣れてる時ほどルアー(カラー)チェンジする様にしてます。 そうすれば、そのルアー(カラー)が効いてるのかどうかがわかるので。. ルアーの開発時点では、プロたちが透明なルアーで釣りをしていることも多いようですし、ルアーのカラーなんて何でも良いというのが正直なところです。（笑） 私も、昔はアユカラーと金/黒があれば何とかなると思っていました。 今は、中古ルアーを買うことが多くなり、カラーを選べないので、何でも良いと思うようになりました。 ただ、メガバスの赤トラカラーは一度爆釣を味わってから、特別に一軍カラーになっています。. ## カテゴリQ&Aランキング. 女性一人で釣りに行く人って、いますか？私は、ソロキャンプに良く行くのですが、釣りもやってみたいと思っています。3回ほど、川をせき止めてある管理釣り場でニジマスを釣りに行きました。とても楽かったので、また行きたくて仕方ありません。その時は、夫や知り合いと一緒だったのですが、今度は一人で行ってみたいのです。でも、女性のソロキャンプは今では珍しくないですが、女性で一人で釣りに行くのって、あまり聞いた事がありません。若い女性なら、まだいいとして、けっこう年齢の女性だと、変な人と見られるのかなぁ、なんて、考えてしまいます。ちなみに、今年で還暦です。人に迷惑かけなければ、好きにやればいいとは思うので... 先日とてもいやな思いをしました。とある漁港で一人で釣りをしていました。（本人女性）そこへ中年の男性が相次いで二人きました。船で作業していたので、地元の漁師のようです。その二人の男性は私のほうを見てわざと見せつけるように放尿したのです。しかも終わってからも５分以上下半身を出して見せつけていました。距離は少しあったのですが明らかに見せつける感じでした。別にトイレしたいのなら、近くに公衆トイレもあり、海に向かってしなくても堤防向けてすればいいと思います。セクハラだし、猥褻物陳列罪ですよね。自分の職場に放尿もびっくりですがそんな人の捕った魚食べたくないし、出荷前に魚にかけてても不思議じゃない。こ... 釣りにおいて、大きい魚を釣り上げるのは実力もあるとは思うのですが、7割くらいは運だと思ってるのですが、技術なんですか？大きい群れが回ってきてたら大きいのが釣れますし、イサキなんかは棚を上にすると比較的大きいのがかかるイメージです。. 「管理釣り場」を執拗に「釣り堀」と呼びたがる人、あるいは逆に「管理釣り場」は「管理釣り場」と呼ぶ人に質問です。Q1.自然渓流を、石で区間を区切ったマス釣り場があります。例えば奥多摩フィッシングセンターなどです（各地に、同様の管理釣り場は沢山あると思います）。水は常に上流から下流に流れていて、滞留していません。さて、これは「釣り堀」ですか？Q2.各地に、区間を決めた冬季釣り場があります。放流の主体はニジマスで、放流量は、区間外に比べて、非常に多いです。さて、これは「釣り堀」ですか？Q3.各地にキャッチアンドリリース区間が設定されてる川があります。魚が目視できたり、ライズ量やライズの発生率が... 釣りでの自己防衛手段について、皆さんはなどのような事をされてますか？私の場合、自分の命を守るためのライフジャケットは当たり前。また、他人に怪我をさせたり不注意で他人の道具を破損させてしまった事態に備えて損害保険に加入しています。自動車保険に追加するかたちで最高二億。動機としては、私のホームは中国地方の漁港·防波堤では最高峰の存在なので、広島福山倉敷岡山方面からヤカラ、家族連れ、ジジババ軍団などがやって来て、不規則な動きやモノの配置をするから。だから怖く思って加入しました。. SNSに魚を大量に並べて自慢してるやつらは何とかならないのでしょうか？？食べきれないから親戚に配る？笑わせるな。自分で食べきれる分だけで良いだろうが、、、自己満足で、俺はこんなに釣れたんだぞ！！って、、大量のアオリイカ、大量のキジハタ、大量のアジ、食べきれもしない大型の魚。何とかならないのでしょうか？？. ## あなたも答えてみませんか. ファンドリィの柔軟剤を買ってみたのですが、 よく見ると果肉入りジュースのように 白いゴミのようなものが浮いていました。 説明欄や注意書きを見てみたのですが、 そのような表記はありませんでした。 ※見. 探しているハロー！モーニングの動画があります。 イントロクイズのやつです。 たしか、けっこう最後のほうのやつだったかと。 ミキティがブギートレイン'03歌ってたぐらいしか覚えてないです。 情報量... bubble Web版について クレカ登録をしたいのですが、失敗コードがでてきて一生登録できないんです！ どなたかおしえてくださいませ（；\\_；）. アロカシアクプレアについて教えて下さい。 アロカシア初心者です。 1週間前にお迎えしたクプレアの葉裏が溶けてきました。 触るとねちょっとした紫の絵の具みたいなのが指に付きます。 まだ購入時のま... ## 総合Q&Aランキング. 僻地という表現は失礼ですか？今日、ある人(50代くらい)と話す予定がありましてその人に自分の将来のことを説明しなければいけませんでした。そのときに、医師や薬剤師の数が少ない僻地の医療現場で医師または薬剤師として働き、仕事を通して社会に貢献したいという言い方をしたのですが、その返答で「僻地という言い方... 国宝のラストについての見解を お聞かせくださいませ 原作も読み 映画も観ました 面白かったの一言 ただラストを 皆さま どうとらえたか？を 自由にお聞かせ願えたらと思いました よろしくお願いいたします. もっちゅりんについて質問です。 今日もっちゅりんを購入し、翌日友人と食べる予定なのですが冷蔵庫に入れるか、冷房の効いた部屋においておくかで迷っています。この時期はどちら方がいいでしょうか( ; ; )、. ## 質問内容."},{"title":"木曽川シーバス絶好調！雨の濁りで確率UP！ - 釣り情報 - イシグロ","url":"https://www.ishiguro-gr.com/enjoy/fishing/detail.php?id=37011","snippet":"メーカー：メガバスルアー：カゲロウ100F カラー：シークレットデッドスティッキング. 釣行日: 2026/05/10. 釣行時間: 19:00～23:00. 釣場: その他. ポイント. 釣魚: シーバス."}],"collectedAt":"2026-06-08T15:19:24.334Z","usedInKnowledgeIds":[]}],"supportingExperiences":[],"contradictingExperiences":[],"confidenceScore":0.2,"sourceKnowledgeId":null,"tags":[],"folderId":"6a2b6d83362131396b29a428","createdAt":"2026-06-08T15:19:23.351Z","__v":0},{"_id":"6a26d389f644c1ac1c16febd","field":"釣り","type":"hypothesis","category":"ルアーカラー","subcategory":"","content":"日中の紫外線が十分に存在する時間帯において、ケイムラ（紫外線発光）カラーのルアーは、非ケイムラカラーに比べて高い集魚効果を発揮する。","webSources":[{"field":"釣り","query":"釣れるルアーカラーについて知りたい","results":[{"title":"ルアーカラーに迷ったらこの色！ルアーカラーを決めるためのポイント | ElephantMask","url":"https://elephantmask.site/archives/645","snippet":"ElephantMask  明石・神戸 釣りブログ　たまに映画レビュー etc. # ルアーカラーに迷ったらこの色！ルアーカラーを決めるためのポイント. ## 色の見えるメカニズム. ちなみに可視光線は380～750nmの電磁波で、この範囲外で波長の短いものが**紫外線**、長いものが**赤外線**というわけです。. 対象物から反射した光を、目の奥の網膜にある視細胞、**錐体（すいたい）細胞**と**桿体（かんたい）細胞**で処理されます。. **錐体細胞が光の色**を処理し、**桿体細胞が光の明るさ**を処理し、脳に信号を送ることで、. ## Advertisement. ## 魚の色の見え方. ※ちなみに「オプシン」というのが魚の目の蛋白質（視物質）のことです。. | 赤型  (M/LWS) | 緑型  （RH2) | 青型  （SWS2) | 紫外線型  （SWS1) | 桿体型  （RH1) |. | 爬虫類 | 〇 | 〇 | 〇 | 〇 | 〇 |. | 霊長類 | ◎  (L-M) | × | × | 〇  (S) | 〇 |. つまり、**上を見る場合は長波長の黄緑～青**を見ることができ、**下を見るときは短波長の緑～藍を**見ることができるという感じで. これはやはり水の中という環境を考えると、上方向（水面）と下方向（ボトム）では光の度合が違う。. >  それはまさに別世界だった。視界に飛び込む色は、白っぽい青や緑、紫、黄色。. > サンゴ礁に逃げ込んだ魚は、動いていて敵から距離があれば、周囲の派手な色と区別がつかないという。じっと動かない魚でも、離れた所からは模様がぼやけて見つけにくくなるらしい。. ## 魚は光る…？. > 海の中では蛍光色の緑や赤、オレンジが輝く「光のショー」が展開しているが、残念ながら、魚には見えるのに人間には見えない――。米自然史博物館が中心となった研究チームは８日、魚における生物発光に関する論文をオンライン誌「プロス・ワン」に発表した。. > これまでに発光することが確認された魚は約１８０種類に上る。魚は体内にある器官で青い光を「吸収」し、別の色に変えて放出させることで発光するという。. サメ、エイ、ウナギ、エソ、ハゼ、カレイ、カサゴが光って見えてるわけですよｗ. 先ほどの**「魚の色の見え方」**であった、**紫外線を反射させて仲間と連絡を取る**というのと. ブラックライトを当てると光る**チャート系**や**ケイムラ**もこの感じなのかもしれないです。. ## 結果、どんな時にどのルアーカラーがいいの？. ### まずは考えない、好きなルアーカラーでキャスティング！. ### 赤系. アムズデザイン(ima) ペンシルベイト ヨイチ バリスタ 99mm 36g ルアー. ### ゴールド系. **金ベースは濁り潮で、夏の釣りに強い**ってコアマン泉さんの「シーバスノート」に書いてあったので信じてますｗ. ### チャート系. ダイワ(DAIWA) 鉄板バイブレーション モアザン リアルスティール 14g/18g/26g 各種. ### ケイムラ. マリア(Maria) ミノー デュプレックス 65 65mm 18g ケイムラコットンキャンディ B09H ルアー. J-STAGE Webサイト 資料「錐体オプシン遺伝子と色覚の進化多様性：魚類と霊長類に注目して」. CNN Webサイト Odd News「180種の魚が海中で「発光」　識別や目くらましに利用か」. ### スマホをブラックライト化して釣りに利用しようと思ったら… 2019.09.07. 応援お願いします ソルトルアーランキング 夜釣りに重宝するのが蓄光タイプのグローカラーのルアーです。 以前にいろいろと調べた結果、夜でも魚の [&he[…]. * 最近の釣果とお気に入りルアー（ワーム）を紹介します！【ダイワ 月下美人ドリビーム0.9インチ】. 応援お願いします ソルトルアーランキング 1年以上ブログサボってました…。 お久しぶりです。 あんまり釣りに行ってなかったってのもありますが [&he[…]. 忙しくてなかなか釣りに行けない日々が続く割に、釣り道具が増えていく…という釣り人あるあるな状態のElephantMaskです。 でも今週末こ [&he[…]. ### 釣りに興味が無い方にも楽しんでもらえるように「釣り用語クイズ」を作ってみました！ 2019.10.18. 応援お願いします ソルトルアーランキング 釣りの話題は久しぶりですね。 子どもの体調不良や、台風やら、週末になるといろいろあるもので…。 ま [&he[…]. * 「たこいなり」明石・魚の棚の名店「浪花」の味を再現⁉【タコ料理】. 応援お願いします ソルトルアーランキング 突然ですが、タコ料理と言えば？ タコブツ、タコ焼き、タコときゅうりの酢の物、タコの天ぷら、タコの唐 [&he[…]."},{"title":"ルアーのカラーについて質問です。 私は青系や緑系の鮮やかな色が ...","url":"https://detail.chiebukuro.yahoo.co.jp/qa/question_detail/q12227536712","snippet":"ルアーのカラーについて質問です。私は青系や緑系の鮮やかな色が好きで気がつけば持っているルアーは7割ほどナチュラルカラー？になってしまいました。"},{"title":"ルアーカラーは釣果に関係ない？ある？釣り歴10年の筆者の結論","url":"https://www.bepal.net/archives/538683","snippet":"チャート系とは黄色や緑といった蛍光色のようなカラーのことをいいます。 チャート系のカラーは非常に目立つため、活躍する場面としては光量の少ない夜間"},{"title":"ルアーの一番いい色・カラーって何!?【バス釣りの疑問】","url":"https://nojiriko-fishing.net/post-8143","snippet":"泥のような色の中では、黒、赤、白、チャートリュースのルアーは良いオプションでしょう。スピナーベイトやクランクベイトのようなムービングルアーを使う"},{"title":"【釣具解説】ルアーカラー 基本の選び方 | めしだ@AnglersFullness","url":"https://ameblo.jp/meshida1023anglers/entry-12814981150.html","snippet":"ルアーがよく見える時間帯、水の色、天気であればナチュラル系のカラー。 ルアーがあまり見えない時間帯、水の色、天気であればアピール系のカラー。 この"}],"collectedAt":"2026-06-08T14:36:59.089Z","usedInKnowledgeIds":[]}],"supportingExperiences":[],"contradictingExperiences":[],"confidenceScore":0.26,"sourceKnowledgeId":null,"tags":[],"folderId":"6a2b6d85362131396b29a42b","createdAt":"2026-06-08T14:36:58.001Z","__v":0},{"_id":"6a26d389498b8fbdc63a02f5","field":"釣り","type":"hypothesis","category":"ルアーカラー","subcategory":"","content":"夜間や光量が極めて少ない状況下において、チャート系（蛍光色）のルアーは、青や緑などのナチュラル系ルアーより高い釣果をもたらす。","webSources":[{"field":"釣り","query":"釣れるルアーカラーについて知りたい","results":[{"title":"ルアーカラーに迷ったらこの色！ルアーカラーを決めるためのポイント | ElephantMask","url":"https://elephantmask.site/archives/645","snippet":"ElephantMask  明石・神戸 釣りブログ　たまに映画レビュー etc. # ルアーカラーに迷ったらこの色！ルアーカラーを決めるためのポイント. ## 色の見えるメカニズム. ちなみに可視光線は380～750nmの電磁波で、この範囲外で波長の短いものが**紫外線**、長いものが**赤外線**というわけです。. 対象物から反射した光を、目の奥の網膜にある視細胞、**錐体（すいたい）細胞**と**桿体（かんたい）細胞**で処理されます。. **錐体細胞が光の色**を処理し、**桿体細胞が光の明るさ**を処理し、脳に信号を送ることで、. ## Advertisement. ## 魚の色の見え方. ※ちなみに「オプシン」というのが魚の目の蛋白質（視物質）のことです。. | 赤型  (M/LWS) | 緑型  （RH2) | 青型  （SWS2) | 紫外線型  （SWS1) | 桿体型  （RH1) |. | 爬虫類 | 〇 | 〇 | 〇 | 〇 | 〇 |. | 霊長類 | ◎  (L-M) | × | × | 〇  (S) | 〇 |. つまり、**上を見る場合は長波長の黄緑～青**を見ることができ、**下を見るときは短波長の緑～藍を**見ることができるという感じで. これはやはり水の中という環境を考えると、上方向（水面）と下方向（ボトム）では光の度合が違う。. >  それはまさに別世界だった。視界に飛び込む色は、白っぽい青や緑、紫、黄色。. > サンゴ礁に逃げ込んだ魚は、動いていて敵から距離があれば、周囲の派手な色と区別がつかないという。じっと動かない魚でも、離れた所からは模様がぼやけて見つけにくくなるらしい。. ## 魚は光る…？. > 海の中では蛍光色の緑や赤、オレンジが輝く「光のショー」が展開しているが、残念ながら、魚には見えるのに人間には見えない――。米自然史博物館が中心となった研究チームは８日、魚における生物発光に関する論文をオンライン誌「プロス・ワン」に発表した。. > これまでに発光することが確認された魚は約１８０種類に上る。魚は体内にある器官で青い光を「吸収」し、別の色に変えて放出させることで発光するという。. サメ、エイ、ウナギ、エソ、ハゼ、カレイ、カサゴが光って見えてるわけですよｗ. 先ほどの**「魚の色の見え方」**であった、**紫外線を反射させて仲間と連絡を取る**というのと. ブラックライトを当てると光る**チャート系**や**ケイムラ**もこの感じなのかもしれないです。. ## 結果、どんな時にどのルアーカラーがいいの？. ### まずは考えない、好きなルアーカラーでキャスティング！. ### 赤系. アムズデザイン(ima) ペンシルベイト ヨイチ バリスタ 99mm 36g ルアー. ### ゴールド系. **金ベースは濁り潮で、夏の釣りに強い**ってコアマン泉さんの「シーバスノート」に書いてあったので信じてますｗ. ### チャート系. ダイワ(DAIWA) 鉄板バイブレーション モアザン リアルスティール 14g/18g/26g 各種. ### ケイムラ. マリア(Maria) ミノー デュプレックス 65 65mm 18g ケイムラコットンキャンディ B09H ルアー. J-STAGE Webサイト 資料「錐体オプシン遺伝子と色覚の進化多様性：魚類と霊長類に注目して」. CNN Webサイト Odd News「180種の魚が海中で「発光」　識別や目くらましに利用か」. ### スマホをブラックライト化して釣りに利用しようと思ったら… 2019.09.07. 応援お願いします ソルトルアーランキング 夜釣りに重宝するのが蓄光タイプのグローカラーのルアーです。 以前にいろいろと調べた結果、夜でも魚の [&he[…]. * 最近の釣果とお気に入りルアー（ワーム）を紹介します！【ダイワ 月下美人ドリビーム0.9インチ】. 応援お願いします ソルトルアーランキング 1年以上ブログサボってました…。 お久しぶりです。 あんまり釣りに行ってなかったってのもありますが [&he[…]. 忙しくてなかなか釣りに行けない日々が続く割に、釣り道具が増えていく…という釣り人あるあるな状態のElephantMaskです。 でも今週末こ [&he[…]. ### 釣りに興味が無い方にも楽しんでもらえるように「釣り用語クイズ」を作ってみました！ 2019.10.18. 応援お願いします ソルトルアーランキング 釣りの話題は久しぶりですね。 子どもの体調不良や、台風やら、週末になるといろいろあるもので…。 ま [&he[…]. * 「たこいなり」明石・魚の棚の名店「浪花」の味を再現⁉【タコ料理】. 応援お願いします ソルトルアーランキング 突然ですが、タコ料理と言えば？ タコブツ、タコ焼き、タコときゅうりの酢の物、タコの天ぷら、タコの唐 [&he[…]."},{"title":"ルアーのカラーについて質問です。 私は青系や緑系の鮮やかな色が ...","url":"https://detail.chiebukuro.yahoo.co.jp/qa/question_detail/q12227536712","snippet":"ルアーのカラーについて質問です。私は青系や緑系の鮮やかな色が好きで気がつけば持っているルアーは7割ほどナチュラルカラー？になってしまいました。"},{"title":"ルアーカラーは釣果に関係ない？ある？釣り歴10年の筆者の結論","url":"https://www.bepal.net/archives/538683","snippet":"チャート系とは黄色や緑といった蛍光色のようなカラーのことをいいます。 チャート系のカラーは非常に目立つため、活躍する場面としては光量の少ない夜間"},{"title":"ルアーの一番いい色・カラーって何!?【バス釣りの疑問】","url":"https://nojiriko-fishing.net/post-8143","snippet":"泥のような色の中では、黒、赤、白、チャートリュースのルアーは良いオプションでしょう。スピナーベイトやクランクベイトのようなムービングルアーを使う"},{"title":"【釣具解説】ルアーカラー 基本の選び方 | めしだ@AnglersFullness","url":"https://ameblo.jp/meshida1023anglers/entry-12814981150.html","snippet":"ルアーがよく見える時間帯、水の色、天気であればナチュラル系のカラー。 ルアーがあまり見えない時間帯、水の色、天気であればアピール系のカラー。 この"}],"collectedAt":"2026-06-08T14:36:59.087Z","usedInKnowledgeIds":[]}],"supportingExperiences":[],"contradictingExperiences":[],"confidenceScore":0.2,"sourceKnowledgeId":null,"tags":[],"folderId":"6a2b6d87362131396b29a430","createdAt":"2026-06-08T14:36:57.874Z","__v":0},{"_id":"6a26d38851b888e33b7dc207","field":"釣り","type":"hypothesis","category":"ルアーカラー","subcategory":"","content":"夏の濁り潮の環境において、金ベースのルアーは他のカラー（ナチュラル系など）に比べて魚のバイト数を増加させる。","webSources":[{"field":"釣り","query":"釣れるルアーカラーについて知りたい","results":[{"title":"ルアーカラーに迷ったらこの色！ルアーカラーを決めるためのポイント | ElephantMask","url":"https://elephantmask.site/archives/645","snippet":"ElephantMask  明石・神戸 釣りブログ　たまに映画レビュー etc. # ルアーカラーに迷ったらこの色！ルアーカラーを決めるためのポイント. ## 色の見えるメカニズム. ちなみに可視光線は380～750nmの電磁波で、この範囲外で波長の短いものが**紫外線**、長いものが**赤外線**というわけです。. 対象物から反射した光を、目の奥の網膜にある視細胞、**錐体（すいたい）細胞**と**桿体（かんたい）細胞**で処理されます。. **錐体細胞が光の色**を処理し、**桿体細胞が光の明るさ**を処理し、脳に信号を送ることで、. ## Advertisement. ## 魚の色の見え方. ※ちなみに「オプシン」というのが魚の目の蛋白質（視物質）のことです。. | 赤型  (M/LWS) | 緑型  （RH2) | 青型  （SWS2) | 紫外線型  （SWS1) | 桿体型  （RH1) |. | 爬虫類 | 〇 | 〇 | 〇 | 〇 | 〇 |. | 霊長類 | ◎  (L-M) | × | × | 〇  (S) | 〇 |. つまり、**上を見る場合は長波長の黄緑～青**を見ることができ、**下を見るときは短波長の緑～藍を**見ることができるという感じで. これはやはり水の中という環境を考えると、上方向（水面）と下方向（ボトム）では光の度合が違う。. >  それはまさに別世界だった。視界に飛び込む色は、白っぽい青や緑、紫、黄色。. > サンゴ礁に逃げ込んだ魚は、動いていて敵から距離があれば、周囲の派手な色と区別がつかないという。じっと動かない魚でも、離れた所からは模様がぼやけて見つけにくくなるらしい。. ## 魚は光る…？. > 海の中では蛍光色の緑や赤、オレンジが輝く「光のショー」が展開しているが、残念ながら、魚には見えるのに人間には見えない――。米自然史博物館が中心となった研究チームは８日、魚における生物発光に関する論文をオンライン誌「プロス・ワン」に発表した。. > これまでに発光することが確認された魚は約１８０種類に上る。魚は体内にある器官で青い光を「吸収」し、別の色に変えて放出させることで発光するという。. サメ、エイ、ウナギ、エソ、ハゼ、カレイ、カサゴが光って見えてるわけですよｗ. 先ほどの**「魚の色の見え方」**であった、**紫外線を反射させて仲間と連絡を取る**というのと. ブラックライトを当てると光る**チャート系**や**ケイムラ**もこの感じなのかもしれないです。. ## 結果、どんな時にどのルアーカラーがいいの？. ### まずは考えない、好きなルアーカラーでキャスティング！. ### 赤系. アムズデザイン(ima) ペンシルベイト ヨイチ バリスタ 99mm 36g ルアー. ### ゴールド系. **金ベースは濁り潮で、夏の釣りに強い**ってコアマン泉さんの「シーバスノート」に書いてあったので信じてますｗ. ### チャート系. ダイワ(DAIWA) 鉄板バイブレーション モアザン リアルスティール 14g/18g/26g 各種. ### ケイムラ. マリア(Maria) ミノー デュプレックス 65 65mm 18g ケイムラコットンキャンディ B09H ルアー. J-STAGE Webサイト 資料「錐体オプシン遺伝子と色覚の進化多様性：魚類と霊長類に注目して」. CNN Webサイト Odd News「180種の魚が海中で「発光」　識別や目くらましに利用か」. ### スマホをブラックライト化して釣りに利用しようと思ったら… 2019.09.07. 応援お願いします ソルトルアーランキング 夜釣りに重宝するのが蓄光タイプのグローカラーのルアーです。 以前にいろいろと調べた結果、夜でも魚の [&he[…]. * 最近の釣果とお気に入りルアー（ワーム）を紹介します！【ダイワ 月下美人ドリビーム0.9インチ】. 応援お願いします ソルトルアーランキング 1年以上ブログサボってました…。 お久しぶりです。 あんまり釣りに行ってなかったってのもありますが [&he[…]. 忙しくてなかなか釣りに行けない日々が続く割に、釣り道具が増えていく…という釣り人あるあるな状態のElephantMaskです。 でも今週末こ [&he[…]. ### 釣りに興味が無い方にも楽しんでもらえるように「釣り用語クイズ」を作ってみました！ 2019.10.18. 応援お願いします ソルトルアーランキング 釣りの話題は久しぶりですね。 子どもの体調不良や、台風やら、週末になるといろいろあるもので…。 ま [&he[…]. * 「たこいなり」明石・魚の棚の名店「浪花」の味を再現⁉【タコ料理】. 応援お願いします ソルトルアーランキング 突然ですが、タコ料理と言えば？ タコブツ、タコ焼き、タコときゅうりの酢の物、タコの天ぷら、タコの唐 [&he[…]."},{"title":"ルアーのカラーについて質問です。 私は青系や緑系の鮮やかな色が ...","url":"https://detail.chiebukuro.yahoo.co.jp/qa/question_detail/q12227536712","snippet":"ルアーのカラーについて質問です。私は青系や緑系の鮮やかな色が好きで気がつけば持っているルアーは7割ほどナチュラルカラー？になってしまいました。"},{"title":"ルアーカラーは釣果に関係ない？ある？釣り歴10年の筆者の結論","url":"https://www.bepal.net/archives/538683","snippet":"チャート系とは黄色や緑といった蛍光色のようなカラーのことをいいます。 チャート系のカラーは非常に目立つため、活躍する場面としては光量の少ない夜間"},{"title":"ルアーの一番いい色・カラーって何!?【バス釣りの疑問】","url":"https://nojiriko-fishing.net/post-8143","snippet":"泥のような色の中では、黒、赤、白、チャートリュースのルアーは良いオプションでしょう。スピナーベイトやクランクベイトのようなムービングルアーを使う"},{"title":"【釣具解説】ルアーカラー 基本の選び方 | めしだ@AnglersFullness","url":"https://ameblo.jp/meshida1023anglers/entry-12814981150.html","snippet":"ルアーがよく見える時間帯、水の色、天気であればナチュラル系のカラー。 ルアーがあまり見えない時間帯、水の色、天気であればアピール系のカラー。 この"}],"collectedAt":"2026-06-08T14:36:59.083Z","usedInKnowledgeIds":[]}],"supportingExperiences":[],"contradictingExperiences":[],"confidenceScore":0.2756,"sourceKnowledgeId":null,"tags":[],"folderId":"6a2b6d83362131396b29a428","createdAt":"2026-06-08T14:36:56.979Z","__v":0},{"_id":"6a26d38851b888e33b7dc205","field":"釣り","type":"hypothesis","category":"ルアーカラー","subcategory":"","content":"水が泥で激しく濁っている状況において、黒や赤、白、チャート系のルアーは、視認性が低い状況でも魚に発見されやすく、バイト率が高くなる。","webSources":[{"field":"釣り","query":"釣れるルアーカラーについて知りたい","results":[{"title":"ルアーカラーに迷ったらこの色！ルアーカラーを決めるためのポイント | ElephantMask","url":"https://elephantmask.site/archives/645","snippet":"ElephantMask  明石・神戸 釣りブログ　たまに映画レビュー etc. # ルアーカラーに迷ったらこの色！ルアーカラーを決めるためのポイント. ## 色の見えるメカニズム. ちなみに可視光線は380～750nmの電磁波で、この範囲外で波長の短いものが**紫外線**、長いものが**赤外線**というわけです。. 対象物から反射した光を、目の奥の網膜にある視細胞、**錐体（すいたい）細胞**と**桿体（かんたい）細胞**で処理されます。. **錐体細胞が光の色**を処理し、**桿体細胞が光の明るさ**を処理し、脳に信号を送ることで、. ## Advertisement. ## 魚の色の見え方. ※ちなみに「オプシン」というのが魚の目の蛋白質（視物質）のことです。. | 赤型  (M/LWS) | 緑型  （RH2) | 青型  （SWS2) | 紫外線型  （SWS1) | 桿体型  （RH1) |. | 爬虫類 | 〇 | 〇 | 〇 | 〇 | 〇 |. | 霊長類 | ◎  (L-M) | × | × | 〇  (S) | 〇 |. つまり、**上を見る場合は長波長の黄緑～青**を見ることができ、**下を見るときは短波長の緑～藍を**見ることができるという感じで. これはやはり水の中という環境を考えると、上方向（水面）と下方向（ボトム）では光の度合が違う。. >  それはまさに別世界だった。視界に飛び込む色は、白っぽい青や緑、紫、黄色。. > サンゴ礁に逃げ込んだ魚は、動いていて敵から距離があれば、周囲の派手な色と区別がつかないという。じっと動かない魚でも、離れた所からは模様がぼやけて見つけにくくなるらしい。. ## 魚は光る…？. > 海の中では蛍光色の緑や赤、オレンジが輝く「光のショー」が展開しているが、残念ながら、魚には見えるのに人間には見えない――。米自然史博物館が中心となった研究チームは８日、魚における生物発光に関する論文をオンライン誌「プロス・ワン」に発表した。. > これまでに発光することが確認された魚は約１８０種類に上る。魚は体内にある器官で青い光を「吸収」し、別の色に変えて放出させることで発光するという。. サメ、エイ、ウナギ、エソ、ハゼ、カレイ、カサゴが光って見えてるわけですよｗ. 先ほどの**「魚の色の見え方」**であった、**紫外線を反射させて仲間と連絡を取る**というのと. ブラックライトを当てると光る**チャート系**や**ケイムラ**もこの感じなのかもしれないです。. ## 結果、どんな時にどのルアーカラーがいいの？. ### まずは考えない、好きなルアーカラーでキャスティング！. ### 赤系. アムズデザイン(ima) ペンシルベイト ヨイチ バリスタ 99mm 36g ルアー. ### ゴールド系. **金ベースは濁り潮で、夏の釣りに強い**ってコアマン泉さんの「シーバスノート」に書いてあったので信じてますｗ. ### チャート系. ダイワ(DAIWA) 鉄板バイブレーション モアザン リアルスティール 14g/18g/26g 各種. ### ケイムラ. マリア(Maria) ミノー デュプレックス 65 65mm 18g ケイムラコットンキャンディ B09H ルアー. J-STAGE Webサイト 資料「錐体オプシン遺伝子と色覚の進化多様性：魚類と霊長類に注目して」. CNN Webサイト Odd News「180種の魚が海中で「発光」　識別や目くらましに利用か」. ### スマホをブラックライト化して釣りに利用しようと思ったら… 2019.09.07. 応援お願いします ソルトルアーランキング 夜釣りに重宝するのが蓄光タイプのグローカラーのルアーです。 以前にいろいろと調べた結果、夜でも魚の [&he[…]. * 最近の釣果とお気に入りルアー（ワーム）を紹介します！【ダイワ 月下美人ドリビーム0.9インチ】. 応援お願いします ソルトルアーランキング 1年以上ブログサボってました…。 お久しぶりです。 あんまり釣りに行ってなかったってのもありますが [&he[…]. 忙しくてなかなか釣りに行けない日々が続く割に、釣り道具が増えていく…という釣り人あるあるな状態のElephantMaskです。 でも今週末こ [&he[…]. ### 釣りに興味が無い方にも楽しんでもらえるように「釣り用語クイズ」を作ってみました！ 2019.10.18. 応援お願いします ソルトルアーランキング 釣りの話題は久しぶりですね。 子どもの体調不良や、台風やら、週末になるといろいろあるもので…。 ま [&he[…]. * 「たこいなり」明石・魚の棚の名店「浪花」の味を再現⁉【タコ料理】. 応援お願いします ソルトルアーランキング 突然ですが、タコ料理と言えば？ タコブツ、タコ焼き、タコときゅうりの酢の物、タコの天ぷら、タコの唐 [&he[…]."},{"title":"ルアーのカラーについて質問です。 私は青系や緑系の鮮やかな色が ...","url":"https://detail.chiebukuro.yahoo.co.jp/qa/question_detail/q12227536712","snippet":"ルアーのカラーについて質問です。私は青系や緑系の鮮やかな色が好きで気がつけば持っているルアーは7割ほどナチュラルカラー？になってしまいました。"},{"title":"ルアーカラーは釣果に関係ない？ある？釣り歴10年の筆者の結論","url":"https://www.bepal.net/archives/538683","snippet":"チャート系とは黄色や緑といった蛍光色のようなカラーのことをいいます。 チャート系のカラーは非常に目立つため、活躍する場面としては光量の少ない夜間"},{"title":"ルアーの一番いい色・カラーって何!?【バス釣りの疑問】","url":"https://nojiriko-fishing.net/post-8143","snippet":"泥のような色の中では、黒、赤、白、チャートリュースのルアーは良いオプションでしょう。スピナーベイトやクランクベイトのようなムービングルアーを使う"},{"title":"【釣具解説】ルアーカラー 基本の選び方 | めしだ@AnglersFullness","url":"https://ameblo.jp/meshida1023anglers/entry-12814981150.html","snippet":"ルアーがよく見える時間帯、水の色、天気であればナチュラル系のカラー。 ルアーがあまり見えない時間帯、水の色、天気であればアピール系のカラー。 この"}],"collectedAt":"2026-06-08T14:36:59.088Z","usedInKnowledgeIds":[]}],"supportingExperiences":[],"contradictingExperiences":[],"confidenceScore":0.2,"sourceKnowledgeId":null,"tags":[],"folderId":"6a2b6d83362131396b29a428","createdAt":"2026-06-08T14:36:56.854Z","__v":0},{"_id":"6a21790e9afc50bc440d66df","field":"読書","type":"hypothesis","category":"気づき","subcategory":"","content":"アイデアは寝かせることで発酵する（外山滋比古）","webSources":[],"supportingExperiences":[],"contradictingExperiences":[],"confidenceScore":0.6,"sourceKnowledgeId":null,"tags":["思考","発酵"],"folderId":null,"createdAt":"2026-06-04T13:09:34.954Z","__v":0},{"_id":"6a21790e9afc50bc440d66dd","field":"筋トレ","type":"hypothesis","category":"回復・睡眠","subcategory":"","content":"7時間以下だと翌日パフォーマンスが落ちる","webSources":[],"supportingExperiences":[],"contradictingExperiences":[],"confidenceScore":0.75,"sourceKnowledgeId":null,"tags":["睡眠","回復"],"folderId":null,"createdAt":"2026-06-04T13:09:34.606Z","__v":0},{"_id":"6a21790e9afc50bc440d66db","field":"筋トレ","type":"hypothesis","category":"種目・フォーム","subcategory":"","content":"スクワットは膝をつま先方向へ","webSources":[],"supportingExperiences":[],"contradictingExperiences":[],"confidenceScore":0.5,"sourceKnowledgeId":null,"tags":["スクワット"],"folderId":null,"createdAt":"2026-06-04T13:09:34.257Z","__v":0},{"_id":"6a21790d9afc50bc440d66d9","field":"筋トレ","type":"hypothesis","category":"種目・フォーム","subcategory":"","content":"ベンチは肩甲骨を寄せてアーチを作る","webSources":[],"supportingExperiences":[],"contradictingExperiences":[],"confidenceScore":0.85,"sourceKnowledgeId":null,"tags":["ベンチ","フォーム"],"folderId":null,"createdAt":"2026-06-04T13:09:33.913Z","__v":0}]